{
  "best_sm": [
    0.250725869342
  ],
  "scales": [
    240.0
  ],
  "theory_cov_current": [
    [
      0.0
    ]
  ],
  "theory_cov_conservative": [
    [
      0.0
    ]
  ],
  "theory_cov_aggressive": [
    [
      0.0
    ]
  ],
  "LO": {
    "SM": [
      0.250725869342
    ],
    "O3pQ3": [
      0.0487269828707
    ],
    "O3pl1": [
      -0.000608551011492
    ],
    "O3pl2": [
      -0.0304000685936
    ],
    "OQe": [
      -0.0580925641137
    ],
    "OQl13": [
      0.427622032414
    ],
    "OQl1M": [
      0.213811016207
    ],
    "Oeb": [
      0.0842472807197
    ],
    "Ol1b": [
      0.0368006657752
    ],
    "Oll1221": [
      0.0304000685936
    ],
    "OpD": [
      -0.00608627356207
    ],
    "OpQM": [
      0.0243634914353
    ],
    "OpWB": [
      -0.0124090560034
    ],
    "Opdi": [
      -0.00289391097989
    ],
    "Ope": [
      -0.010456804031
    ],
    "Opl1": [
      0.0297915175822
    ],
    "O3pQ3*O3pQ3": [
      0.00330491187559
    ],
    "O3pQ3*OQe": [
      -0.0172584546537
    ],
    "O3pQ3*OQl13": [
      0.0429243843807
    ],
    "O3pQ3*OQl1M": [
      0.0214621921903
    ],
    "O3pQ3*OpQM": [
      0.00330491187559
    ],
    "O3pQ3*OpWB": [
      0.000896158782099
    ],
    "O3pl1*O3pQ3": [
      0.000129017117528
    ],
    "O3pl1*O3pl1": [
      0.000335413686256
    ],
    "O3pl1*O3pl2": [
      3.68928673786e-05
    ],
    "O3pl1*OQe": [
      0.00352181037096
    ],
    "O3pl1*OQl13": [
      0.00704362074193
    ],
    "O3pl1*OQl1M": [
      0.00352181037096
    ],
    "O3pl1*Oeb": [
      -0.00510741695587
    ],
    "O3pl1*Ol1b": [
      -0.00510741695587
    ],
    "O3pl1*Oll1221": [
      -3.68928673786e-05
    ],
    "O3pl1*OpD": [
      0.00112770280478
    ],
    "O3pl1*OpQM": [
      6.45085587638e-05
    ],
    "O3pl1*OpWB": [
      0.00144205351124
    ],
    "O3pl1*Opdi": [
      -9.35519156696e-05
    ],
    "O3pl1*Ope": [
      0.000633934505133
    ],
    "O3pl1*Opl1": [
      0.000633934505133
    ],
    "O3pl2*O3pQ3": [
      -0.00295403028319
    ],
    "O3pl2*O3pl2": [
      0.00092148864906
    ],
    "O3pl2*OQe": [
      0.00352181037096
    ],
    "O3pl2*OQl13": [
      -0.0259242078842
    ],
    "O3pl2*OQl1M": [
      -0.0129621039421
    ],
    "O3pl2*Oeb": [
      -0.00510741695587
    ],
    "O3pl2*Ol1b": [
      -0.00223100784692
    ],
    "O3pl2*Oll1221": [
      -0.00184297729812
    ],
    "O3pl2*OpD": [
      0.000368974957096
    ],
    "O3pl2*OpQM": [
      -0.00147701514159
    ],
    "O3pl2*OpWB": [
      0.000752288056023
    ],
    "O3pl2*Opdi": [
      0.000175440796204
    ],
    "O3pl2*Ope": [
      0.000633934505133
    ],
    "O3pl2*Opl1": [
      -0.00180608443074
    ],
    "OQe*OQe": [
      0.0573752023654
    ],
    "OQe*OQl13": [
      0.0
    ],
    "OQe*OQl1M": [
      0.0
    ],
    "OQl13*OQl13": [
      0.229500809462
    ],
    "OQl13*OQl1M": [
      0.229500809462
    ],
    "OQl1M*OQl1M": [
      0.0573752023654
    ],
    "Oeb*O3pQ3": [
      0.0
    ],
    "Oeb*OQe": [
      0.0
    ],
    "Oeb*OQl13": [
      0.0
    ],
    "Oeb*OQl1M": [
      0.0
    ],
    "Oeb*Oeb": [
      0.0573752023654
    ],
    "Oeb*Ol1b": [
      0.0
    ],
    "Oeb*Oll1221": [
      0.00510741695587
    ],
    "Oeb*OpD": [
      -0.0117815764227
    ],
    "Oeb*OpQM": [
      0.0
    ],
    "Oeb*OpWB": [
      -0.01907509424
    ],
    "Oeb*Opdi": [
      -0.00862922732683
    ],
    "Oeb*Ope": [
      -0.00287640910894
    ],
    "Oeb*Opl1": [
      0.0
    ],
    "Ol1b*O3pQ3": [
      0.0
    ],
    "Ol1b*OQe": [
      0.0
    ],
    "Ol1b*OQl13": [
      0.0
    ],
    "Ol1b*OQl1M": [
      0.0
    ],
    "Ol1b*Ol1b": [
      0.0573752023654
    ],
    "Ol1b*Oll1221": [
      0.00223100784692
    ],
    "Ol1b*OpD": [
      -0.00532813528206
    ],
    "Ol1b*OpQM": [
      0.0
    ],
    "Ol1b*OpWB": [
      -0.0137037122577
    ],
    "Ol1b*Opdi": [
      0.0107310960952
    ],
    "Ol1b*Ope": [
      0.0
    ],
    "Ol1b*Opl1": [
      -0.00287640910894
    ],
    "Oll1221*O3pQ3": [
      0.00295403028319
    ],
    "Oll1221*OQe": [
      -0.00352181037096
    ],
    "Oll1221*OQl13": [
      0.0259242078842
    ],
    "Oll1221*OQl1M": [
      0.0129621039421
    ],
    "Oll1221*Oll1221": [
      0.00092148864906
    ],
    "Oll1221*OpD": [
      -0.000368974957096
    ],
    "Oll1221*OpQM": [
      0.00147701514159
    ],
    "Oll1221*OpWB": [
      -0.000752288056023
    ],
    "Oll1221*Opdi": [
      -0.000175440796204
    ],
    "Oll1221*Ope": [
      -0.000633934505133
    ],
    "Oll1221*Opl1": [
      0.00180608443074
    ],
    "OpD*O3pQ3": [
      -0.000325867554637
    ],
    "OpD*OQe": [
      0.00757874699928
    ],
    "OpD*OQl13": [
      0.00870405285789
    ],
    "OpD*OQl1M": [
      0.00435202642895
    ],
    "OpD*OpD": [
      0.00106131263448
    ],
    "OpD*OpQM": [
      -0.000162933777318
    ],
    "OpD*OpWB": [
      0.00249062220857
    ],
    "OpD*Opdi": [
      0.000387703813374
    ],
    "OpD*Ope": [
      0.00138401298234
    ],
    "OpD*Opl1": [
      0.000758727847681
    ],
    "OpQM*OQe": [
      -0.00862922732683
    ],
    "OpQM*OQl13": [
      0.0214621921903
    ],
    "OpQM*OQl1M": [
      0.0107310960952
    ],
    "OpQM*OpQM": [
      0.000826227968898
    ],
    "OpQM*OpWB": [
      0.000448079391049
    ],
    "OpWB*OQe": [
      -0.00296094829304
    ],
    "OpWB*OQl13": [
      0.00482086737858
    ],
    "OpWB*OQl1M": [
      0.00241043368929
    ],
    "OpWB*OpWB": [
      0.00246721724686
    ],
    "Opdi*O3pQ3": [
      0.0
    ],
    "Opdi*OQe": [
      0.0
    ],
    "Opdi*OQl13": [
      0.0
    ],
    "Opdi*OQl1M": [
      0.0
    ],
    "Opdi*OpQM": [
      0.0
    ],
    "Opdi*OpWB": [
      0.000152918601212
    ],
    "Opdi*Opdi": [
      0.000826227968898
    ],
    "Opdi*Ope": [
      0.000216305887062
    ],
    "Opdi*Opl1": [
      -0.000268992711873
    ],
    "Ope*O3pQ3": [
      -0.00247917981949
    ],
    "Ope*OQe": [
      0.0164839143131
    ],
    "Ope*OQl13": [
      0.0
    ],
    "Ope*OQl1M": [
      0.0
    ],
    "Ope*OpQM": [
      -0.00123958990974
    ],
    "Ope*OpWB": [
      5.28081525491e-05
    ],
    "Ope*Ope": [
      0.00122000946794
    ],
    "Ope*Opl1": [
      0.0
    ],
    "Opl1*O3pQ3": [
      0.00308304740071
    ],
    "Opl1*OQe": [
      0.0
    ],
    "Opl1*OQl13": [
      0.0329678286261
    ],
    "Opl1*OQl1M": [
      0.0164839143131
    ],
    "Opl1*OpQM": [
      0.00154152370036
    ],
    "Opl1*OpWB": [
      0.000689765455221
    ],
    "Opl1*Opl1": [
      0.00122000946794
    ]
  }
}
