{
  "best_sm": [
    592.0
  ],
  "scales": [
    344.0
  ],
  "theory_cov": [
    [
      0.0
    ]
  ],
  "LO": {
    "SM": [
      572.9125185
    ],
    "O11qq": [
      0.0
    ],
    "O13qq": [
      0.0
    ],
    "O1dt": [
      0.0
    ],
    "O1qd": [
      0.0
    ],
    "O1qt": [
      0.0
    ],
    "O1qu": [
      0.0
    ],
    "O1ut": [
      0.0
    ],
    "O3pl1": [
      -34.72857926
    ],
    "O3pl2": [
      -34.71655852
    ],
    "O81qq": [
      33.00027259
    ],
    "O83qq": [
      12.52285333
    ],
    "O8dt": [
      10.3319163
    ],
    "O8qd": [
      5.805165926
    ],
    "O8qt": [
      42.82264296
    ],
    "O8qu": [
      37.21988593
    ],
    "O8ut": [
      22.7176
    ],
    "Oll1221": [
      34.73379704
    ],
    "OpD": [
      -60.53581926
    ],
    "OpWB": [
      -129.7312593
    ],
    "OtG": [
      163.8489926
    ],
    "OtW": [
      24.10980296
    ],
    "OtZ": [
      -21.26016296
    ],
    "O11qq*O11qq": [
      31.88856963
    ],
    "O11qq*O13qq": [
      15.26379407
    ],
    "O13qq*O13qq": [
      32.14954
    ],
    "O1dt*O11qq": [
      0.07047481481
    ],
    "O1dt*O13qq": [
      -0.2605681481
    ],
    "O1dt*O1dt": [
      11.82183259
    ],
    "O1dt*O1qt": [
      0.06984666667
    ],
    "O1dt*O1ut": [
      0.002947407407
    ],
    "O1qd*O11qq": [
      -0.05260718519
    ],
    "O1qd*O13qq": [
      -0.2688745926
    ],
    "O1qd*O1dt": [
      2.158031333
    ],
    "O1qd*O1qd": [
      6.313227926
    ],
    "O1qd*O1qt": [
      -0.003862
    ],
    "O1qd*O1qu": [
      0.5483735556
    ],
    "O1qd*O1ut": [
      -0.3626738519
    ],
    "O1qt*O11qq": [
      9.459157037
    ],
    "O1qt*O13qq": [
      4.927823704
    ],
    "O1qt*O1qt": [
      45.33310296
    ],
    "O1qt*O1ut": [
      0.08701925926
    ],
    "O1qu*O11qq": [
      0.2309888889
    ],
    "O1qu*O13qq": [
      -0.3329348148
    ],
    "O1qu*O1dt": [
      0.2873244444
    ],
    "O1qu*O1qt": [
      0.1233237037
    ],
    "O1qu*O1qu": [
      38.96248444
    ],
    "O1qu*O1ut": [
      7.55038963
    ],
    "O1ut*O11qq": [
      -0.4933340741
    ],
    "O1ut*O13qq": [
      -0.8215703704
    ],
    "O1ut*O1ut": [
      20.08176519
    ],
    "O3pl1*O11qq": [
      0.0913839037
    ],
    "O3pl1*O13qq": [
      -0.09541017037
    ],
    "O3pl1*O1dt": [
      0.04054094074
    ],
    "O3pl1*O1qd": [
      -0.01817113333
    ],
    "O3pl1*O1qt": [
      -0.1365946148
    ],
    "O3pl1*O1qu": [
      -0.03648646667
    ],
    "O3pl1*O1ut": [
      -0.1909323926
    ],
    "O3pl1*O3pl1": [
      0.5263472074
    ],
    "O3pl1*O3pl2": [
      1.052377556
    ],
    "O3pl1*O81qq": [
      -0.006816392593
    ],
    "O3pl1*O83qq": [
      -0.02007765185
    ],
    "O3pl1*O8dt": [
      -0.002697874074
    ],
    "O3pl1*O8qd": [
      -0.06105187407
    ],
    "O3pl1*O8qt": [
      0.01205205185
    ],
    "O3pl1*O8qu": [
      -0.06871091111
    ],
    "O3pl1*O8ut": [
      -0.1475040963
    ],
    "O3pl1*Oll1221": [
      -1.052773481
    ],
    "O3pl1*OtG": [
      -5.00011237
    ],
    "O3pl1*OtW": [
      -0.7931879259
    ],
    "O3pl1*OtZ": [
      0.5456750148
    ],
    "O3pl2*O11qq": [
      -0.1926295037
    ],
    "O3pl2*O13qq": [
      -0.3459902444
    ],
    "O3pl2*O1dt": [
      0.0109704963
    ],
    "O3pl2*O1qd": [
      0.004714422222
    ],
    "O3pl2*O1qt": [
      -0.2060146889
    ],
    "O3pl2*O1qu": [
      -0.142642837
    ],
    "O3pl2*O1ut": [
      -0.07863542963
    ],
    "O3pl2*O3pl2": [
      0.5261650593
    ],
    "O3pl2*O81qq": [
      0.07318723704
    ],
    "O3pl2*O83qq": [
      0.007512644444
    ],
    "O3pl2*O8dt": [
      -0.003933503704
    ],
    "O3pl2*O8qd": [
      -0.04432187407
    ],
    "O3pl2*O8qt": [
      -0.02071765185
    ],
    "O3pl2*O8qu": [
      -0.1088776519
    ],
    "O3pl2*O8ut": [
      -0.05464868889
    ],
    "O3pl2*Oll1221": [
      -1.052591333
    ],
    "O3pl2*OtG": [
      -4.959155407
    ],
    "O3pl2*OtW": [
      -0.8517146667
    ],
    "O3pl2*OtZ": [
      0.6465290148
    ],
    "O81qq*O11qq": [
      0.0
    ],
    "O81qq*O13qq": [
      0.0
    ],
    "O81qq*O1dt": [
      0.0
    ],
    "O81qq*O1qd": [
      0.0
    ],
    "O81qq*O1qt": [
      0.0
    ],
    "O81qq*O1qu": [
      0.0
    ],
    "O81qq*O1ut": [
      0.0
    ],
    "O81qq*O81qq": [
      7.020162519
    ],
    "O81qq*O83qq": [
      3.772496667
    ],
    "O83qq*O11qq": [
      0.0
    ],
    "O83qq*O13qq": [
      0.0
    ],
    "O83qq*O1dt": [
      0.0
    ],
    "O83qq*O1qd": [
      0.0
    ],
    "O83qq*O1qt": [
      0.0
    ],
    "O83qq*O1qu": [
      0.0
    ],
    "O83qq*O1ut": [
      0.0
    ],
    "O83qq*O83qq": [
      7.060303778
    ],
    "O8dt*O11qq": [
      0.0
    ],
    "O8dt*O13qq": [
      0.0
    ],
    "O8dt*O1dt": [
      0.0
    ],
    "O8dt*O1qd": [
      0.0
    ],
    "O8dt*O1qt": [
      0.0
    ],
    "O8dt*O1qu": [
      0.0
    ],
    "O8dt*O1ut": [
      0.0
    ],
    "O8dt*O81qq": [
      0.06926118519
    ],
    "O8dt*O83qq": [
      -0.03409785185
    ],
    "O8dt*O8dt": [
      2.655728889
    ],
    "O8dt*O8qt": [
      0.01515259259
    ],
    "O8dt*O8ut": [
      -0.06299422222
    ],
    "O8qd*O11qq": [
      0.0
    ],
    "O8qd*O13qq": [
      0.0
    ],
    "O8qd*O1dt": [
      0.0
    ],
    "O8qd*O1qd": [
      0.0
    ],
    "O8qd*O1qt": [
      0.0
    ],
    "O8qd*O1qu": [
      0.0
    ],
    "O8qd*O1ut": [
      0.0
    ],
    "O8qd*O81qq": [
      0.01455274074
    ],
    "O8qd*O83qq": [
      -0.0741262963
    ],
    "O8qd*O8dt": [
      0.3858252593
    ],
    "O8qd*O8qd": [
      1.430197333
    ],
    "O8qd*O8qt": [
      0.001947851852
    ],
    "O8qd*O8qu": [
      -0.1121099259
    ],
    "O8qd*O8ut": [
      -0.04273666667
    ],
    "O8qt*O11qq": [
      0.0
    ],
    "O8qt*O13qq": [
      0.0
    ],
    "O8qt*O1dt": [
      0.0
    ],
    "O8qt*O1qd": [
      0.0
    ],
    "O8qt*O1qt": [
      0.0
    ],
    "O8qt*O1qu": [
      0.0
    ],
    "O8qt*O1ut": [
      0.0
    ],
    "O8qt*O81qq": [
      2.197481185
    ],
    "O8qt*O83qq": [
      1.118706593
    ],
    "O8qt*O8qt": [
      10.10063778
    ],
    "O8qt*O8ut": [
      -0.01486140741
    ],
    "O8qu*O11qq": [
      0.0
    ],
    "O8qu*O13qq": [
      0.0
    ],
    "O8qu*O1dt": [
      0.0
    ],
    "O8qu*O1qd": [
      0.0
    ],
    "O8qu*O1qt": [
      0.0
    ],
    "O8qu*O1qu": [
      0.0
    ],
    "O8qu*O1ut": [
      0.0
    ],
    "O8qu*O81qq": [
      0.03502044444
    ],
    "O8qu*O83qq": [
      -0.1591852593
    ],
    "O8qu*O8dt": [
      -0.1006318519
    ],
    "O8qu*O8qt": [
      -0.1486992593
    ],
    "O8qu*O8qu": [
      8.778678519
    ],
    "O8qu*O8ut": [
      1.579623037
    ],
    "O8ut*O11qq": [
      0.0
    ],
    "O8ut*O13qq": [
      0.0
    ],
    "O8ut*O1dt": [
      0.0
    ],
    "O8ut*O1qd": [
      0.0
    ],
    "O8ut*O1qt": [
      0.0
    ],
    "O8ut*O1qu": [
      0.0
    ],
    "O8ut*O1ut": [
      0.0
    ],
    "O8ut*O81qq": [
      0.04031607407
    ],
    "O8ut*O83qq": [
      0.01164518519
    ],
    "O8ut*O8ut": [
      4.458656222
    ],
    "Oll1221*O11qq": [
      0.04368334815
    ],
    "Oll1221*O13qq": [
      0.1232040889
    ],
    "Oll1221*O1dt": [
      0.1660818667
    ],
    "Oll1221*O1qd": [
      -0.01062657778
    ],
    "Oll1221*O1qt": [
      0.1436426074
    ],
    "Oll1221*O1qu": [
      0.2719255704
    ],
    "Oll1221*O1ut": [
      -0.2180114667
    ],
    "Oll1221*O81qq": [
      0.02915342222
    ],
    "Oll1221*O83qq": [
      0.04072401481
    ],
    "Oll1221*O8dt": [
      -0.01655154074
    ],
    "Oll1221*O8qd": [
      -0.03357346667
    ],
    "Oll1221*O8qt": [
      -0.000767762963
    ],
    "Oll1221*O8qu": [
      -0.0427048
    ],
    "Oll1221*O8ut": [
      -0.05837783704
    ],
    "Oll1221*Oll1221": [
      0.5264262815
    ],
    "Oll1221*OtG": [
      4.922075185
    ],
    "Oll1221*OtW": [
      0.7523211111
    ],
    "Oll1221*OtZ": [
      -0.7562692593
    ],
    "OpD*O11qq": [
      -0.008819111111
    ],
    "OpD*O13qq": [
      -0.4696102222
    ],
    "OpD*O1dt": [
      0.1329112593
    ],
    "OpD*O1qd": [
      0.02058185185
    ],
    "OpD*O1qt": [
      -0.01867762963
    ],
    "OpD*O1qu": [
      0.3700594074
    ],
    "OpD*O1ut": [
      -0.2639939259
    ],
    "OpD*O3pl1": [
      1.835631926
    ],
    "OpD*O3pl2": [
      1.839604519
    ],
    "OpD*O81qq": [
      0.01352059259
    ],
    "OpD*O83qq": [
      -0.03027992593
    ],
    "OpD*O8dt": [
      -0.02527
    ],
    "OpD*O8qd": [
      -0.0223897037
    ],
    "OpD*O8qt": [
      0.002637925926
    ],
    "OpD*O8qu": [
      -0.1217642963
    ],
    "OpD*O8ut": [
      -0.02657125926
    ],
    "OpD*Oll1221": [
      -1.83530363
    ],
    "OpD*OpD": [
      1.599699852
    ],
    "OpD*OpWB": [
      6.841857407
    ],
    "OpD*OtG": [
      -8.669632593
    ],
    "OpD*OtW": [
      -1.362359111
    ],
    "OpD*OtZ": [
      1.105285333
    ],
    "OpWB*O11qq": [
      0.08636392593
    ],
    "OpWB*O13qq": [
      -0.4720923704
    ],
    "OpWB*O1dt": [
      0.188158
    ],
    "OpWB*O1qd": [
      -0.05593140741
    ],
    "OpWB*O1qt": [
      -0.03499014815
    ],
    "OpWB*O1qu": [
      0.1564624444
    ],
    "OpWB*O1ut": [
      -0.2392531111
    ],
    "OpWB*O3pl1": [
      3.928415259
    ],
    "OpWB*O3pl2": [
      3.930035926
    ],
    "OpWB*O81qq": [
      0.03109177778
    ],
    "OpWB*O83qq": [
      0.0006282962963
    ],
    "OpWB*O8dt": [
      -0.03731755556
    ],
    "OpWB*O8qd": [
      -0.06175266667
    ],
    "OpWB*O8qt": [
      -0.09927755556
    ],
    "OpWB*O8qu": [
      -0.1245108889
    ],
    "OpWB*O8ut": [
      -0.01610266667
    ],
    "OpWB*Oll1221": [
      -3.932546667
    ],
    "OpWB*OpWB": [
      7.343368667
    ],
    "OpWB*OtG": [
      -18.57182741
    ],
    "OpWB*OtW": [
      -2.733687926
    ],
    "OpWB*OtZ": [
      2.384405407
    ],
    "OtG*O11qq": [
      0.0
    ],
    "OtG*O13qq": [
      0.0
    ],
    "OtG*O1dt": [
      0.0
    ],
    "OtG*O1qd": [
      0.0
    ],
    "OtG*O1qt": [
      0.0
    ],
    "OtG*O1qu": [
      0.0
    ],
    "OtG*O1ut": [
      0.0
    ],
    "OtG*O81qq": [
      0.06385081481
    ],
    "OtG*O83qq": [
      -0.03124674074
    ],
    "OtG*O8dt": [
      -0.05097333333
    ],
    "OtG*O8qd": [
      -0.00951362963
    ],
    "OtG*O8qt": [
      -0.009204444444
    ],
    "OtG*O8qu": [
      -0.1097444444
    ],
    "OtG*O8ut": [
      0.01054451852
    ],
    "OtG*OtG": [
      26.71842741
    ],
    "OtG*OtW": [
      13.64775333
    ],
    "OtG*OtZ": [
      -12.23709704
    ],
    "OtW*O11qq": [
      -0.1074259259
    ],
    "OtW*O13qq": [
      -0.2360185185
    ],
    "OtW*O1dt": [
      0.06076666667
    ],
    "OtW*O1qd": [
      -0.01593607407
    ],
    "OtW*O1qt": [
      0.3430925926
    ],
    "OtW*O1qu": [
      0.2099703704
    ],
    "OtW*O1ut": [
      -0.205977037
    ],
    "OtW*O81qq": [
      0.07757155556
    ],
    "OtW*O83qq": [
      0.08809251852
    ],
    "OtW*O8dt": [
      -0.02789703704
    ],
    "OtW*O8qd": [
      -0.07738918519
    ],
    "OtW*O8qt": [
      -0.006513333333
    ],
    "OtW*O8qu": [
      -0.1783311111
    ],
    "OtW*O8ut": [
      -0.06827696296
    ],
    "OtW*OtW": [
      57.51407111
    ],
    "OtZ*O11qq": [
      -0.3779118519
    ],
    "OtZ*O13qq": [
      -0.3359711111
    ],
    "OtZ*O1dt": [
      0.04825925926
    ],
    "OtZ*O1qd": [
      -0.1112501481
    ],
    "OtZ*O1qt": [
      -0.1311711111
    ],
    "OtZ*O1qu": [
      0.06502518519
    ],
    "OtZ*O1ut": [
      -0.002903703704
    ],
    "OtZ*O81qq": [
      0.1444626667
    ],
    "OtZ*O83qq": [
      0.07317325926
    ],
    "OtZ*O8dt": [
      -0.06279703704
    ],
    "OtZ*O8qd": [
      -0.1052454815
    ],
    "OtZ*O8qt": [
      -0.09463407407
    ],
    "OtZ*O8qu": [
      -0.01882148148
    ],
    "OtZ*O8ut": [
      -0.1058473333
    ],
    "OtZ*OtW": [
      -101.4236222
    ],
    "OtZ*OtZ": [
      44.71706074
    ]
  },
  "NLO_QCD": {
    "SM": [
      739.0571489
    ],
    "O11qq": [
      0.0
    ],
    "O13qq": [
      0.0
    ],
    "O1dt": [
      0.0
    ],
    "O1qd": [
      0.0
    ],
    "O1qt": [
      0.0
    ],
    "O1qu": [
      0.0
    ],
    "O1ut": [
      0.0
    ],
    "O3pl1": [
      -44.79986724
    ],
    "O3pl2": [
      -44.78436049
    ],
    "O81qq": [
      42.57035164
    ],
    "O83qq": [
      16.1544808
    ],
    "O8dt": [
      13.32817202
    ],
    "O8qd": [
      7.488664044
    ],
    "O8qt": [
      55.24120942
    ],
    "O8qu": [
      48.01365284
    ],
    "O8ut": [
      29.305704
    ],
    "Oll1221": [
      44.80659818
    ],
    "OpD": [
      -78.09120684
    ],
    "OpWB": [
      -167.3533244
    ],
    "OtG": [
      211.3652004
    ],
    "OtW": [
      31.10164582
    ],
    "OtZ": [
      -27.42561022
    ],
    "O11qq*O11qq": [
      41.13625482
    ],
    "O11qq*O13qq": [
      19.69029436
    ],
    "O13qq*O13qq": [
      41.4729066
    ],
    "O1dt*O11qq": [
      0.09091251111
    ],
    "O1dt*O13qq": [
      -0.3361329111
    ],
    "O1dt*O1dt": [
      15.25016404
    ],
    "O1dt*O1qt": [
      0.0901022
    ],
    "O1dt*O1ut": [
      0.003802155556
    ],
    "O1qd*O11qq": [
      -0.06786326889
    ],
    "O1qd*O13qq": [
      -0.3468482244
    ],
    "O1qd*O1dt": [
      2.78386042
    ],
    "O1qd*O1qd": [
      8.144064024
    ],
    "O1qd*O1qt": [
      -0.00498198
    ],
    "O1qd*O1qu": [
      0.7074018867
    ],
    "O1qd*O1ut": [
      -0.4678492689
    ],
    "O1qt*O11qq": [
      12.20231258
    ],
    "O1qt*O13qq": [
      6.356892578
    ],
    "O1qt*O1qt": [
      58.47970282
    ],
    "O1qt*O1ut": [
      0.1122548444
    ],
    "O1qu*O11qq": [
      0.2979756667
    ],
    "O1qu*O13qq": [
      -0.4294859111
    ],
    "O1qu*O1dt": [
      0.3706485333
    ],
    "O1qu*O1qt": [
      0.1590875778
    ],
    "O1qu*O1qu": [
      50.26160493
    ],
    "O1qu*O1ut": [
      9.740002622
    ],
    "O1ut*O11qq": [
      -0.6364009556
    ],
    "O1ut*O13qq": [
      -1.059825778
    ],
    "O1ut*O1ut": [
      25.90547709
    ],
    "O3pl1*O11qq": [
      0.1178852358
    ],
    "O3pl1*O13qq": [
      -0.1230791198
    ],
    "O3pl1*O1dt": [
      0.05229781356
    ],
    "O3pl1*O1qd": [
      -0.023440762
    ],
    "O3pl1*O1qt": [
      -0.1762070531
    ],
    "O3pl1*O1qu": [
      -0.047067542
    ],
    "O3pl1*O1ut": [
      -0.2463027864
    ],
    "O3pl1*O3pl1": [
      0.6789878976
    ],
    "O3pl1*O3pl2": [
      1.357567047
    ],
    "O3pl1*O81qq": [
      -1.300091718
    ],
    "O3pl1*O83qq": [
      -0.5147552264
    ],
    "O3pl1*O8dt": [
      -0.4058580131
    ],
    "O3pl1*O8qd": [
      -0.3033590087
    ],
    "O3pl1*O8qt": [
      -1.657689847
    ],
    "O3pl1*O8qu": [
      -1.539386336
    ],
    "O3pl1*O8ut": [
      -1.074602871
    ],
    "O3pl1*Oll1221": [
      -1.358077791
    ],
    "O3pl1*OtG": [
      -6.450144958
    ],
    "O3pl1*OtW": [
      -1.023212424
    ],
    "O3pl1*OtZ": [
      0.7039207691
    ],
    "O3pl2*O11qq": [
      -0.2484920598
    ],
    "O3pl2*O13qq": [
      -0.4463274153
    ],
    "O3pl2*O1dt": [
      0.01415194022
    ],
    "O3pl2*O1qd": [
      0.006081604667
    ],
    "O3pl2*O1qt": [
      -0.2657589487
    ],
    "O3pl2*O1qu": [
      -0.1840092598
    ],
    "O3pl2*O1ut": [
      -0.1014397042
    ],
    "O3pl2*O3pl2": [
      0.6787529264
    ],
    "O3pl2*O81qq": [
      -1.196667067
    ],
    "O3pl2*O83qq": [
      -0.4788749753
    ],
    "O3pl2*O8dt": [
      -0.4095993953
    ],
    "O3pl2*O8qd": [
      -0.2832894753
    ],
    "O3pl2*O8qt": [
      -1.699888231
    ],
    "O3pl2*O8qu": [
      -1.590909987
    ],
    "O3pl2*O8ut": [
      -0.9604483822
    ],
    "O3pl2*Oll1221": [
      -1.35784282
    ],
    "O3pl2*OtG": [
      -6.397310476
    ],
    "O3pl2*OtW": [
      -1.09871192
    ],
    "O3pl2*OtZ": [
      0.8340224291
    ],
    "O81qq*O11qq": [
      0.0
    ],
    "O81qq*O13qq": [
      0.0
    ],
    "O81qq*O1dt": [
      0.0
    ],
    "O81qq*O1qd": [
      0.0
    ],
    "O81qq*O1qt": [
      0.0
    ],
    "O81qq*O1qu": [
      0.0
    ],
    "O81qq*O1ut": [
      0.0
    ],
    "O81qq*O81qq": [
      9.056009649
    ],
    "O81qq*O83qq": [
      4.8665207
    ],
    "O83qq*O11qq": [
      0.0
    ],
    "O83qq*O13qq": [
      0.0
    ],
    "O83qq*O1dt": [
      0.0
    ],
    "O83qq*O1qd": [
      0.0
    ],
    "O83qq*O1qt": [
      0.0
    ],
    "O83qq*O1qu": [
      0.0
    ],
    "O83qq*O1ut": [
      0.0
    ],
    "O83qq*O83qq": [
      9.107791873
    ],
    "O8dt*O11qq": [
      0.0
    ],
    "O8dt*O13qq": [
      0.0
    ],
    "O8dt*O1dt": [
      0.0
    ],
    "O8dt*O1qd": [
      0.0
    ],
    "O8dt*O1qt": [
      0.0
    ],
    "O8dt*O1qu": [
      0.0
    ],
    "O8dt*O1ut": [
      0.0
    ],
    "O8dt*O81qq": [
      0.08934692889
    ],
    "O8dt*O83qq": [
      -0.04398622889
    ],
    "O8dt*O8dt": [
      3.425890267
    ],
    "O8dt*O8qt": [
      0.01954684444
    ],
    "O8dt*O8ut": [
      -0.08126254667
    ],
    "O8qd*O11qq": [
      0.0
    ],
    "O8qd*O13qq": [
      0.0
    ],
    "O8qd*O1dt": [
      0.0
    ],
    "O8qd*O1qd": [
      0.0
    ],
    "O8qd*O1qt": [
      0.0
    ],
    "O8qd*O1qu": [
      0.0
    ],
    "O8qd*O1ut": [
      0.0
    ],
    "O8qd*O81qq": [
      0.01877303556
    ],
    "O8qd*O83qq": [
      -0.09562292222
    ],
    "O8qd*O8dt": [
      0.4977145844
    ],
    "O8qd*O8qd": [
      1.84495456
    ],
    "O8qd*O8qt": [
      0.002512728889
    ],
    "O8qd*O8qu": [
      -0.1446218044
    ],
    "O8qd*O8ut": [
      -0.0551303
    ],
    "O8qt*O11qq": [
      0.0
    ],
    "O8qt*O13qq": [
      0.0
    ],
    "O8qt*O1dt": [
      0.0
    ],
    "O8qt*O1qd": [
      0.0
    ],
    "O8qt*O1qt": [
      0.0
    ],
    "O8qt*O1qu": [
      0.0
    ],
    "O8qt*O1ut": [
      0.0
    ],
    "O8qt*O81qq": [
      2.834750729
    ],
    "O8qt*O83qq": [
      1.443131504
    ],
    "O8qt*O8qt": [
      13.02982273
    ],
    "O8qt*O8ut": [
      -0.01917121556
    ],
    "O8qu*O11qq": [
      0.0
    ],
    "O8qu*O13qq": [
      0.0
    ],
    "O8qu*O1dt": [
      0.0
    ],
    "O8qu*O1qd": [
      0.0
    ],
    "O8qu*O1qt": [
      0.0
    ],
    "O8qu*O1qu": [
      0.0
    ],
    "O8qu*O1ut": [
      0.0
    ],
    "O8qu*O81qq": [
      0.04517637333
    ],
    "O8qu*O83qq": [
      -0.2053489844
    ],
    "O8qu*O8dt": [
      -0.1298150889
    ],
    "O8qu*O8qt": [
      -0.1918220444
    ],
    "O8qu*O8qu": [
      11.32449529
    ],
    "O8qu*O8ut": [
      2.037713718
    ],
    "O8ut*O11qq": [
      0.0
    ],
    "O8ut*O13qq": [
      0.0
    ],
    "O8ut*O1dt": [
      0.0
    ],
    "O8ut*O1qd": [
      0.0
    ],
    "O8ut*O1qt": [
      0.0
    ],
    "O8ut*O1qu": [
      0.0
    ],
    "O8ut*O1ut": [
      0.0
    ],
    "O8ut*O81qq": [
      0.05200773556
    ],
    "O8ut*O83qq": [
      0.01502228889
    ],
    "O8ut*O8ut": [
      5.751666527
    ],
    "Oll1221*O11qq": [
      0.05635151911
    ],
    "Oll1221*O13qq": [
      0.1589332747
    ],
    "Oll1221*O1dt": [
      0.214245608
    ],
    "Oll1221*O1qd": [
      -0.01370828533
    ],
    "Oll1221*O1qt": [
      0.1852989636
    ],
    "Oll1221*O1qu": [
      0.3507839858
    ],
    "Oll1221*O1ut": [
      -0.281234792
    ],
    "Oll1221*O81qq": [
      1.32814874
    ],
    "Oll1221*O83qq": [
      0.5447626236
    ],
    "Oll1221*O8dt": [
      0.381812308
    ],
    "Oll1221*O8qd": [
      0.1822223613
    ],
    "Oll1221*O8qt": [
      1.675116122
    ],
    "Oll1221*O8qu": [
      1.397045633
    ],
    "Oll1221*O8ut": [
      0.8144395124
    ],
    "Oll1221*Oll1221": [
      0.6790899031
    ],
    "Oll1221*OtG": [
      6.349476989
    ],
    "Oll1221*OtW": [
      0.9704942333
    ],
    "Oll1221*OtZ": [
      -0.9755873444
    ],
    "OpD*O11qq": [
      -0.01137665333
    ],
    "OpD*O13qq": [
      -0.6057971867
    ],
    "OpD*O1dt": [
      0.1714555244
    ],
    "OpD*O1qd": [
      0.02655058889
    ],
    "OpD*O1qt": [
      -0.02409414222
    ],
    "OpD*O1qu": [
      0.4773766356
    ],
    "OpD*O1ut": [
      -0.3405521644
    ],
    "OpD*O3pl1": [
      2.367965184
    ],
    "OpD*O3pl2": [
      2.373089829
    ],
    "OpD*O81qq": [
      -2.230883669
    ],
    "OpD*O83qq": [
      -0.89779786
    ],
    "OpD*O8dt": [
      -0.73521486
    ],
    "OpD*O8qd": [
      -0.4238429733
    ],
    "OpD*O8qt": [
      -2.914728053
    ],
    "OpD*O8qu": [
      -2.680875898
    ],
    "OpD*O8ut": [
      -1.587860522
    ],
    "OpD*Oll1221": [
      -2.367541682
    ],
    "OpD*OpD": [
      2.063612809
    ],
    "OpD*OpWB": [
      8.825996056
    ],
    "OpD*OtG": [
      -11.18382604
    ],
    "OpD*OtW": [
      -1.757443253
    ],
    "OpD*OtZ": [
      1.42581808
    ],
    "OpWB*O11qq": [
      0.1114094644
    ],
    "OpWB*O13qq": [
      -0.6089991578
    ],
    "OpWB*O1dt": [
      0.24272382
    ],
    "OpWB*O1qd": [
      -0.07215151556
    ],
    "OpWB*O1qt": [
      -0.04513729111
    ],
    "OpWB*O1qu": [
      0.2018365533
    ],
    "OpWB*O1ut": [
      -0.3086365133
    ],
    "OpWB*O3pl1": [
      5.067655684
    ],
    "OpWB*O3pl2": [
      5.069746344
    ],
    "OpWB*O81qq": [
      -4.77484814
    ],
    "OpWB*O83qq": [
      -1.852508609
    ],
    "OpWB*O8dt": [
      -1.55173498
    ],
    "OpWB*O8qd": [
      -0.9162842289
    ],
    "OpWB*O8qt": [
      -6.364661913
    ],
    "OpWB*O8qu": [
      -5.565443847
    ],
    "OpWB*O8ut": [
      -3.350224218
    ],
    "OpWB*Oll1221": [
      -5.0729852
    ],
    "OpWB*OpWB": [
      9.47294558
    ],
    "OpWB*OtG": [
      -23.95765736
    ],
    "OpWB*OtW": [
      -3.526457424
    ],
    "OpWB*OtZ": [
      3.075882976
    ],
    "OtG*O11qq": [
      0.0
    ],
    "OtG*O13qq": [
      0.0
    ],
    "OtG*O1dt": [
      0.0
    ],
    "OtG*O1qd": [
      0.0
    ],
    "OtG*O1qt": [
      0.0
    ],
    "OtG*O1qu": [
      0.0
    ],
    "OtG*O1ut": [
      0.0
    ],
    "OtG*O81qq": [
      6.836093751
    ],
    "OtG*O83qq": [
      2.816549593
    ],
    "OtG*O8dt": [
      1.8947606
    ],
    "OtG*O8qd": [
      1.240894573
    ],
    "OtG*O8qt": [
      8.266613356
    ],
    "OtG*O8qu": [
      6.886401267
    ],
    "OtG*O8ut": [
      4.80029554
    ],
    "OtG*OtG": [
      34.46677136
    ],
    "OtG*OtW": [
      17.6056018
    ],
    "OtG*OtZ": [
      -15.78585518
    ],
    "OtW*O11qq": [
      -0.1385794444
    ],
    "OtW*O13qq": [
      -0.3044638889
    ],
    "OtW*O1dt": [
      0.078389
    ],
    "OtW*O1qd": [
      -0.02055753556
    ],
    "OtW*O1qt": [
      0.4425894444
    ],
    "OtW*O1qu": [
      0.2708617778
    ],
    "OtW*O1ut": [
      -0.2657103778
    ],
    "OtW*O81qq": [
      0.5984420844
    ],
    "OtW*O83qq": [
      0.009402571111
    ],
    "OtW*O8dt": [
      0.2662980444
    ],
    "OtW*O8qd": [
      0.08398626222
    ],
    "OtW*O8qt": [
      0.7484924
    ],
    "OtW*O8qu": [
      0.3435298667
    ],
    "OtW*O8ut": [
      0.10987274
    ],
    "OtW*OtW": [
      74.19315173
    ],
    "OtZ*O11qq": [
      -0.4875062889
    ],
    "OtZ*O13qq": [
      -0.4334027333
    ],
    "OtZ*O1dt": [
      0.06225444444
    ],
    "OtZ*O1qd": [
      -0.1435126911
    ],
    "OtZ*O1qt": [
      -0.1692107333
    ],
    "OtZ*O1qu": [
      0.08388248889
    ],
    "OtZ*O1ut": [
      -0.003745777778
    ],
    "OtZ*O81qq": [
      -0.2534700933
    ],
    "OtZ*O83qq": [
      0.1829362378
    ],
    "OtZ*O8dt": [
      -0.3476616889
    ],
    "OtZ*O8qd": [
      -0.2971256044
    ],
    "OtZ*O8qt": [
      -0.7904126222
    ],
    "OtZ*O8qu": [
      -0.5316080444
    ],
    "OtZ*O8ut": [
      -0.3105650156
    ],
    "OtZ*OtW": [
      -130.8364727
    ],
    "OtZ*OtZ": [
      57.68500836
    ]
  }
}
