{
  "best_sm": [
    64.7090326396
  ],
  "scales": [
    240.0
  ],
  "theory_cov_current": [
    [
      0.0
    ]
  ],
  "theory_cov_conservative": [
    [
      0.0
    ]
  ],
  "theory_cov_aggressive": [
    [
      0.0
    ]
  ],
  "LO": {
    "SM": [
      64.7090326396
    ],
    "O3pl1": [
      -8.29565356465
    ],
    "O3pl2": [
      -7.84585585857
    ],
    "Oee1111": [
      -8.29570913985
    ],
    "Ole1111": [
      -6.23670444982
    ],
    "Oll1111": [
      -8.7020455206
    ],
    "Oll1221": [
      7.84585585857
    ],
    "OpD": [
      -13.6982976796
    ],
    "OpWB": [
      -30.1425178407
    ],
    "Ope": [
      0.972244619593
    ],
    "Opl1": [
      -0.44979770608
    ],
    "O3pl1*O3pl1": [
      0.293531426152
    ],
    "O3pl1*O3pl2": [
      0.502916667626
    ],
    "O3pl1*Oee1111": [
      0.502920036824
    ],
    "O3pl1*Ole1111": [
      0.535008177933
    ],
    "O3pl1*Oll1111": [
      0.276018132348
    ],
    "O3pl1*Oll1221": [
      -0.502916667626
    ],
    "O3pl1*OpD": [
      0.920987061391
    ],
    "O3pl1*OpWB": [
      2.03541851409
    ],
    "O3pl1*Ope": [
      -0.100560607491
    ],
    "O3pl1*Opl1": [
      0.084146184678
    ],
    "O3pl2*O3pl2": [
      0.23782403956
    ],
    "O3pl2*Oee1111": [
      0.502920036824
    ],
    "O3pl2*Ole1111": [
      0.37809469675
    ],
    "O3pl2*Oll1111": [
      0.527553820883
    ],
    "O3pl2*Oll1221": [
      -0.475648079119
    ],
    "O3pl2*OpD": [
      0.83044719352
    ],
    "O3pl2*OpWB": [
      1.82736351128
    ],
    "O3pl2*Ope": [
      -0.0589414710236
    ],
    "O3pl2*Opl1": [
      0.0272685885066
    ],
    "Oee1111*Oee1111": [
      1.99920705131
    ],
    "Oee1111*Ole1111": [
      0.0
    ],
    "Oee1111*Oll1111": [
      0.0
    ],
    "Oee1111*Oll1221": [
      -0.502920036824
    ],
    "Oee1111*OpD": [
      0.978013138628
    ],
    "Oee1111*OpWB": [
      1.87829722549
    ],
    "Oee1111*Ope": [
      0.202268120416
    ],
    "Oee1111*Opl1": [
      0.0
    ],
    "Ole1111*Ole1111": [
      1.03699027169
    ],
    "Ole1111*Oll1111": [
      0.0
    ],
    "Ole1111*Oll1221": [
      -0.37809469675
    ],
    "Ole1111*OpD": [
      0.737693408384
    ],
    "Ole1111*OpWB": [
      1.70512056642
    ],
    "Ole1111*Ope": [
      -0.195133768229
    ],
    "Ole1111*Opl1": [
      0.156913481182
    ],
    "Oll1111*Oll1111": [
      1.99920705131
    ],
    "Oll1111*OpD": [
      0.637660281915
    ],
    "Oll1111*OpWB": [
      1.50058345236
    ],
    "Oll1111*Ope": [
      0.0
    ],
    "Oll1111*Opl1": [
      -0.251535688534
    ],
    "Oll1221*Oll1111": [
      -0.527553820883
    ],
    "Oll1221*Oll1221": [
      0.23782403956
    ],
    "Oll1221*OpD": [
      -0.83044719352
    ],
    "Oll1221*OpWB": [
      -1.82736351128
    ],
    "Oll1221*Ope": [
      0.0589414710236
    ],
    "Oll1221*Opl1": [
      -0.0272685885066
    ],
    "OpD*OpD": [
      0.745754572171
    ],
    "OpD*OpWB": [
      3.27061347804
    ],
    "OpD*Ope": [
      -0.116009584703
    ],
    "OpD*Opl1": [
      0.0905398678717
    ],
    "OpWB*OpWB": [
      3.60666320174
    ],
    "Ope*OpWB": [
      -0.297852829076
    ],
    "Ope*Ope": [
      0.0334471613301
    ],
    "Ope*Opl1": [
      -0.0416191364675
    ],
    "Opl1*OpWB": [
      0.208055002812
    ],
    "Opl1*Opl1": [
      0.0284387980857
    ]
  }
}
