{
    "best_sm": [
        0.4887241212760862
    ],
    "theory_cov": [
        [
            0.0
        ]
    ],
    "LO": {
        "SM": [
            0.4887241212760862
        ],
        "OpD": [
            0.0256746740141132
        ],
        "OpWB": [
            0.080171938825406
        ],
        "Opl1": [
            0.0214662907867815
        ],
        "Opl2": [
            0.0214662907867815
        ],
        "O3pl1": [
            0.0214662907867813
        ],
        "O3pl2": [
            0.0214662907867813
        ],
        "Ope": [
            -0.0224865710849247
        ],
        "Opmu": [
            -0.0224865710849247
        ],
        "Oll": [
            0.4298316711978299
        ],
        "Oll1122": [
            0.4298316711978299
        ],
        "OpD*OpD": [
            0.002272736792917
        ],
        "OpD*OpWB": [
            0.0097032673827724
        ],
        "OpD*Opl1": [
            0.0010415761767463
        ],
        "OpD*Opl2": [
            0.0010415761767463
        ],
        "OpD*O3pl1": [
            0.0025980806036647
        ],
        "OpD*O3pl2": [
            0.0025980806036647
        ],
        "OpD*Ope": [
            -0.0005052643128319
        ],
        "OpD*Opmu": [
            -0.0005052643128319
        ],
        "OpD*Oll": [
            0.0152407369856727
        ],
        "OpD*Oll1122": [
            0.0167972414125911
        ],
        "OpWB*OpWB": [
            0.0104216532867383
        ],
        "OpWB*Opl1": [
            0.0007205084595039
        ],
        "OpWB*Opl2": [
            0.0007205084595039
        ],
        "OpWB*O3pl1": [
            0.0055808614138502
        ],
        "OpWB*O3pl2": [
            0.0055808614138502
        ],
        "OpWB*Ope": [
            -0.0003876403406709
        ],
        "OpWB*Opmu": [
            -0.0003876403406709
        ],
        "OpWB*Oll": [
            -0.0286758828765318
        ],
        "OpWB*Oll1122": [
            -0.0238155299221854
        ],
        "Opl1*Opl1": [
            -0.0007814244696231
        ],
        "Opl1*Opl2": [
            -0.0006540640365487
        ],
        "Opl1*O3pl1": [
            -0.0002614740271139
        ],
        "Opl1*O3pl2": [
            0.0006473108755835
        ],
        "Opl1*Ope": [
            0.0006943652322433
        ],
        "Opl1*Opmu": [
            0.0018245079149333
        ],
        "Opl1*Oll": [
            -0.0337362238334226
        ],
        "Opl1*Oll1122": [
            -0.0324348489212902
        ],
        "Opl2*Opl2": [
            -0.0007814244696231
        ],
        "Opl2*O3pl1": [
            0.0006473108755835
        ],
        "Opl2*O3pl2": [
            -0.0002614740271139
        ],
        "Opl2*Ope": [
            0.0018245079149333
        ],
        "Opl2*Opmu": [
            0.0006943652322433
        ],
        "Opl2*Oll": [
            -0.0337362238334226
        ],
        "Opl2*Oll1122": [
            -0.0324348489212902
        ],
        "O3pl1*O3pl1": [
            0.0005199504425091
        ],
        "O3pl1*O3pl2": [
            0.0019486857877158
        ],
        "O3pl1*Ope": [
            -0.0006688632714822
        ],
        "O3pl1*Opmu": [
            0.0004612794112078
        ],
        "O3pl1*Oll": [
            -0.0076780585503344
        ],
        "O3pl1*Oll1122": [
            -0.0063766836382021
        ],
        "O3pl2*O3pl2": [
            0.0005199504425091
        ],
        "O3pl2*Ope": [
            0.0004612794112078
        ],
        "O3pl2*Opmu": [
            -0.0006688632714822
        ],
        "O3pl2*Oll": [
            -0.0076780585503344
        ],
        "O3pl2*Oll1122": [
            -0.0063766836382021
        ],
        "Ope*Ope": [
            -0.000828361215389
        ],
        "Ope*Opmu": [
            -0.0002513046256992
        ],
        "Ope*Oll": [
            0.0454961240409786
        ],
        "Ope*Oll1122": [
            0.044132895537253
        ],
        "Opmu*Opmu": [
            -0.000828361215389
        ],
        "Opmu*Oll": [
            0.0454961240409786
        ],
        "Opmu*Oll1122": [
            0.044132895537253
        ],
        "Oll*Oll": [
            -0.3817127693715471
        ],
        "Oll*Oll1122": [
            -0.7373673734600071
        ],
        "Oll1122*Oll1122": [
            -0.3556546040884599
        ]
    },
    "NLO": {
        "SM": [
            0.4887241212760862
        ],
        "OpD": [
            0.0256746740141132
        ],
        "OpWB": [
            0.080171938825406
        ],
        "Opl1": [
            0.0214662907867815
        ],
        "Opl2": [
            0.0214662907867815
        ],
        "O3pl1": [
            0.0214662907867813
        ],
        "O3pl2": [
            0.0214662907867813
        ],
        "Ope": [
            -0.0224865710849247
        ],
        "Opmu": [
            -0.0224865710849247
        ],
        "Oll": [
            0.4298316711978299
        ],
        "Oll1122": [
            0.4298316711978299
        ],
        "OpD*OpD": [
            0.002272736792917
        ],
        "OpD*OpWB": [
            0.0097032673827724
        ],
        "OpD*Opl1": [
            0.0010415761767463
        ],
        "OpD*Opl2": [
            0.0010415761767463
        ],
        "OpD*O3pl1": [
            0.0025980806036647
        ],
        "OpD*O3pl2": [
            0.0025980806036647
        ],
        "OpD*Ope": [
            -0.0005052643128319
        ],
        "OpD*Opmu": [
            -0.0005052643128319
        ],
        "OpD*Oll": [
            0.0152407369856727
        ],
        "OpD*Oll1122": [
            0.0167972414125911
        ],
        "OpWB*OpWB": [
            0.0104216532867383
        ],
        "OpWB*Opl1": [
            0.0007205084595039
        ],
        "OpWB*Opl2": [
            0.0007205084595039
        ],
        "OpWB*O3pl1": [
            0.0055808614138502
        ],
        "OpWB*O3pl2": [
            0.0055808614138502
        ],
        "OpWB*Ope": [
            -0.0003876403406709
        ],
        "OpWB*Opmu": [
            -0.0003876403406709
        ],
        "OpWB*Oll": [
            -0.0286758828765318
        ],
        "OpWB*Oll1122": [
            -0.0238155299221854
        ],
        "Opl1*Opl1": [
            -0.0007814244696231
        ],
        "Opl1*Opl2": [
            -0.0006540640365487
        ],
        "Opl1*O3pl1": [
            -0.0002614740271139
        ],
        "Opl1*O3pl2": [
            0.0006473108755835
        ],
        "Opl1*Ope": [
            0.0006943652322433
        ],
        "Opl1*Opmu": [
            0.0018245079149333
        ],
        "Opl1*Oll": [
            -0.0337362238334226
        ],
        "Opl1*Oll1122": [
            -0.0324348489212902
        ],
        "Opl2*Opl2": [
            -0.0007814244696231
        ],
        "Opl2*O3pl1": [
            0.0006473108755835
        ],
        "Opl2*O3pl2": [
            -0.0002614740271139
        ],
        "Opl2*Ope": [
            0.0018245079149333
        ],
        "Opl2*Opmu": [
            0.0006943652322433
        ],
        "Opl2*Oll": [
            -0.0337362238334226
        ],
        "Opl2*Oll1122": [
            -0.0324348489212902
        ],
        "O3pl1*O3pl1": [
            0.0005199504425091
        ],
        "O3pl1*O3pl2": [
            0.0019486857877158
        ],
        "O3pl1*Ope": [
            -0.0006688632714822
        ],
        "O3pl1*Opmu": [
            0.0004612794112078
        ],
        "O3pl1*Oll": [
            -0.0076780585503344
        ],
        "O3pl1*Oll1122": [
            -0.0063766836382021
        ],
        "O3pl2*O3pl2": [
            0.0005199504425091
        ],
        "O3pl2*Ope": [
            0.0004612794112078
        ],
        "O3pl2*Opmu": [
            -0.0006688632714822
        ],
        "O3pl2*Oll": [
            -0.0076780585503344
        ],
        "O3pl2*Oll1122": [
            -0.0063766836382021
        ],
        "Ope*Ope": [
            -0.000828361215389
        ],
        "Ope*Opmu": [
            -0.0002513046256992
        ],
        "Ope*Oll": [
            0.0454961240409786
        ],
        "Ope*Oll1122": [
            0.044132895537253
        ],
        "Opmu*Opmu": [
            -0.000828361215389
        ],
        "Opmu*Oll": [
            0.0454961240409786
        ],
        "Opmu*Oll1122": [
            0.044132895537253
        ],
        "Oll*Oll": [
            -0.3817127693715471
        ],
        "Oll*Oll1122": [
            -0.7373673734600071
        ],
        "Oll1122*Oll1122": [
            -0.3556546040884599
        ]
    }
}