{
  "best_sm": [
    0.000490167628368693,
    0.0,
    0.0,
    0.0
  ],
  "scales": [
    250,
    350,
    500,
    1000
  ],
  "theory_cov": [
    [
      0.0
    ],
    [
      0.0
    ],
    [
      0.0
    ],
    [
      0.0
    ]
  ],
  "LO": {
    "SM": [
      0.000490167628368693,
      0.0,
      0.0,
      0.0
    ],
    "OpB": [
      0.007253133582145869,
      0.0,
      0.0,
      0.0
    ],
    "OpW": [
      -0.006834389240712549,
      0.0,
      0.0,
      0.0
    ],
    "OpD": [
      9.062273031169035e-05,
      0.0,
      0.0,
      0.0
    ],
    "O3pl1": [
      0.0007516082680422517,
      0.0,
      0.0,
      0.0
    ],
    "Opl1": [
      0.0007759176074114988,
      0.0,
      0.0,
      0.0
    ],
    "Ope": [
      -3.7324224340726514e-05,
      0.0,
      0.0,
      0.0
    ],
    "Opd": [
      2.0881663102491825e-07,
      0.0,
      0.0,
      0.0
    ],
    "OpWB": [
      0.004675044020887291,
      0.0,
      0.0,
      0.0
    ],
    "O3pl2": [
      -2.430327871883717e-05,
      0.0,
      0.0,
      0.0
    ],
    "Oll": [
      2.396560768596096e-05,
      0.0,
      0.0,
      0.0
    ],
    "Opt": [
      2.5339292650591116e-06,
      0.0,
      0.0,
      0.0
    ],
    "OpQM": [
      2.4054674724613536e-05,
      0.0,
      0.0,
      0.0
    ],
    "O3pQ3": [
      2.134706985401489e-05,
      0.0,
      0.0,
      0.0
    ],
    "OtW": [
      -6.199401386871961e-05,
      0.0,
      0.0,
      0.0
    ],
    "OtZ": [
      -0.00014849278901504288,
      0.0,
      0.0,
      0.0
    ],
    "Otp": [
      6.112368106644632e-06,
      0.0,
      0.0,
      0.0
    ],
    "OpG": [
      -0.0008385134229293773,
      0.0,
      0.0,
      0.0
    ],
    "OtG": [
      -1.9334389785653995e-05,
      0.0,
      0.0,
      0.0
    ],
    "Ocp": [
      0.0007182589647695913,
      0.0,
      0.0,
      0.0
    ],
    "Otap": [
      0.0003353835839438235,
      0.0,
      0.0,
      0.0
    ],
    "Obp": [
      0.0021502019964439994,
      0.0,
      0.0,
      0.0
    ],
    "O3pl3": [
      -2.2286288169829906e-07,
      0.0,
      0.0,
      0.0
    ],
    "O3pq": [
      -1.3757371436214647e-06,
      0.0,
      0.0,
      0.0
    ],
    "Opl2": [
      6.060650409429794e-09,
      0.0,
      0.0,
      0.0
    ],
    "Opl3": [
      6.060650409429794e-09,
      0.0,
      0.0,
      0.0
    ],
    "Opmu": [
      5.279649988229011e-09,
      0.0,
      0.0,
      0.0
    ],
    "Opta": [
      5.279649988229011e-09,
      0.0,
      0.0,
      0.0
    ],
    "OpqMi": [
      -1.5293230005103222e-08,
      0.0,
      0.0,
      0.0
    ],
    "Opui": [
      -2.421428084141343e-08,
      0.0,
      0.0,
      0.0
    ],
    "Opdi": [
      1.6066605596529376e-08,
      0.0,
      0.0,
      0.0
    ],
    "OpB^2": [
      0.025804951684435525,
      0.0,
      0.0,
      0.0
    ],
    "OpB*OpW": [
      -0.046972033760304115,
      0.0,
      0.0,
      0.0
    ],
    "OpB*OpD": [
      0.0013391888330156268,
      0.0,
      0.0,
      0.0
    ],
    "O3pl1*OpB": [
      0.011172274197054277,
      0.0,
      0.0,
      0.0
    ],
    "OpB*Opl1": [
      0.01153469481836389,
      0.0,
      0.0,
      0.0
    ],
    "OpB*Ope": [
      -0.0005790889008497415,
      0.0,
      0.0,
      0.0
    ],
    "OpB*Opd": [
      3.6689689060085737e-06,
      0.0,
      0.0,
      0.0
    ],
    "OpB*OpWB": [
      0.035562201027467065,
      0.0,
      0.0,
      0.0
    ],
    "O3pl2*OpB": [
      -0.00037081248859638653,
      0.0,
      0.0,
      0.0
    ],
    "Oll*OpB": [
      0.0003485171928204164,
      0.0,
      0.0,
      0.0
    ],
    "OpB*Opt": [
      1.7970542037844353e-05,
      0.0,
      0.0,
      0.0
    ],
    "OpB*OpQM": [
      0.00017006329707594888,
      0.0,
      0.0,
      0.0
    ],
    "O3pQ3*OpB": [
      0.00014249133622143553,
      0.0,
      0.0,
      0.0
    ],
    "OpB*OtW": [
      -0.0005027421181040922,
      0.0,
      0.0,
      0.0
    ],
    "OpB*OtZ": [
      -0.0010443401296630845,
      0.0,
      0.0,
      0.0
    ],
    "OpB*Otp": [
      6.524171566506862e-05,
      0.0,
      0.0,
      0.0
    ],
    "OpB*OpG": [
      -0.012481054455548023,
      0.0,
      0.0,
      0.0
    ],
    "OpB*OtG": [
      -0.0002877873689087781,
      0.0,
      0.0,
      0.0
    ],
    "Ocp*OpB": [
      0.010691098087799902,
      0.0,
      0.0,
      0.0
    ],
    "OpB*Otap": [
      0.004992097514761284,
      0.0,
      0.0,
      0.0
    ],
    "Obp*OpB": [
      0.03200519809723536,
      0.0,
      0.0,
      0.0
    ],
    "O3pl3*OpB": [
      -1.1381058211939878e-05,
      0.0,
      0.0,
      0.0
    ],
    "O3pq*OpB": [
      -3.729568592801597e-05,
      0.0,
      0.0,
      0.0
    ],
    "OpB*Opl2": [
      -8.39186728677631e-06,
      0.0,
      0.0,
      0.0
    ],
    "OpB*Opl3": [
      -8.39186728677631e-06,
      0.0,
      0.0,
      0.0
    ],
    "OpB*Opmu": [
      -7.938377658890838e-06,
      0.0,
      0.0,
      0.0
    ],
    "OpB*Opta": [
      -7.938377658890838e-06,
      0.0,
      0.0,
      0.0
    ],
    "OpB*OpqMi": [
      -7.787109846305243e-06,
      0.0,
      0.0,
      0.0
    ],
    "OpB*Opui": [
      -8.468885114098636e-06,
      0.0,
      0.0,
      0.0
    ],
    "OpB*Opdi": [
      -7.137330926030659e-06,
      0.0,
      0.0,
      0.0
    ],
    "OpW^2": [
      0.020252590868420274,
      0.0,
      0.0,
      0.0
    ],
    "OpD*OpW": [
      -0.0012954468116708694,
      0.0,
      0.0,
      0.0
    ],
    "O3pl1*OpW": [
      -0.01078577554195905,
      0.0,
      0.0,
      0.0
    ],
    "Opl1*OpW": [
      -0.01115249817999028,
      0.0,
      0.0,
      0.0
    ],
    "Ope*OpW": [
      0.0005503926842039648,
      0.0,
      0.0,
      0.0
    ],
    "Opd*OpW": [
      -3.297570192218831e-05,
      0.0,
      0.0,
      0.0
    ],
    "OpW*OpWB": [
      -0.030729789383766946,
      0.0,
      0.0,
      0.0
    ],
    "O3pl2*OpW": [
      0.0003647432445597287,
      0.0,
      0.0,
      0.0
    ],
    "Oll*OpW": [
      -0.0003662305318088234,
      0.0,
      0.0,
      0.0
    ],
    "Opt*OpW": [
      -1.694285231309358e-05,
      0.0,
      0.0,
      0.0
    ],
    "OpQM*OpW": [
      -0.00015580589797445702,
      0.0,
      0.0,
      0.0
    ],
    "O3pQ3*OpW": [
      -0.00013925120511363925,
      0.0,
      0.0,
      0.0
    ],
    "OpW*OtW": [
      0.0003563249440096373,
      0.0,
      0.0,
      0.0
    ],
    "OpW*OtZ": [
      0.0010021231318602952,
      0.0,
      0.0,
      0.0
    ],
    "OpW*Otp": [
      -5.844309677365395e-05,
      0.0,
      0.0,
      0.0
    ],
    "OpG*OpW": [
      0.011632591386980716,
      0.0,
      0.0,
      0.0
    ],
    "OpW*OtG": [
      0.00026822356081957345,
      0.0,
      0.0,
      0.0
    ],
    "Ocp*OpW": [
      -0.009964316394615591,
      0.0,
      0.0,
      0.0
    ],
    "OpW*Otap": [
      -0.004652734331061785,
      0.0,
      0.0,
      0.0
    ],
    "Obp*OpW": [
      -0.029829482200441588,
      0.0,
      0.0,
      0.0
    ],
    "O3pl3*OpW": [
      1.5155875224700463e-06,
      0.0,
      0.0,
      0.0
    ],
    "O3pq*OpW": [
      1.4949503059098115e-05,
      0.0,
      0.0,
      0.0
    ],
    "Opl2*OpW": [
      -1.9706793803466336e-06,
      0.0,
      0.0,
      0.0
    ],
    "Opl3*OpW": [
      -1.9706793803466336e-06,
      0.0,
      0.0,
      0.0
    ],
    "Opmu*OpW": [
      -1.871614486501815e-06,
      0.0,
      0.0,
      0.0
    ],
    "Opta*OpW": [
      -1.871614486501815e-06,
      0.0,
      0.0,
      0.0
    ],
    "OpqMi*OpW": [
      -9.76223124633336e-07,
      0.0,
      0.0,
      0.0
    ],
    "Opui*OpW": [
      -1.0419939899624349e-06,
      0.0,
      0.0,
      0.0
    ],
    "Opdi*OpW": [
      -1.763105615718505e-06,
      0.0,
      0.0,
      0.0
    ],
    "OpD^2": [
      6.116361412635379e-06,
      0.0,
      0.0,
      0.0
    ],
    "O3pl1*OpD": [
      8.927400130724228e-05,
      0.0,
      0.0,
      0.0
    ],
    "OpD*Opl1": [
      8.852122588019018e-05,
      0.0,
      0.0,
      0.0
    ],
    "OpD*Ope": [
      2.855549577815533e-06,
      0.0,
      0.0,
      0.0
    ],
    "Opd*OpD": [
      -5.453784363210059e-06,
      0.0,
      0.0,
      0.0
    ],
    "OpD*OpWB": [
      0.0008545060748902228,
      0.0,
      0.0,
      0.0
    ],
    "O3pl2*OpD": [
      7.387898869617186e-07,
      0.0,
      0.0,
      0.0
    ],
    "Oll*OpD": [
      -7.335948688282964e-07,
      0.0,
      0.0,
      0.0
    ],
    "OpD*Opt": [
      4.694727705332261e-07,
      0.0,
      0.0,
      0.0
    ],
    "OpD*OpQM": [
      4.4454605526744975e-06,
      0.0,
      0.0,
      0.0
    ],
    "O3pQ3*OpD": [
      3.940732160259655e-06,
      0.0,
      0.0,
      0.0
    ],
    "OpD*OtW": [
      -1.1368619900666105e-05,
      0.0,
      0.0,
      0.0
    ],
    "OpD*OtZ": [
      -2.752936509188506e-05,
      0.0,
      0.0,
      0.0
    ],
    "OpD*Otp": [
      1.1654501846525659e-06,
      0.0,
      0.0,
      0.0
    ],
    "OpD*OpG": [
      -0.0001667159198962352,
      0.0,
      0.0,
      0.0
    ],
    "OpD*OtG": [
      -3.842878590371484e-06,
      0.0,
      0.0,
      0.0
    ],
    "Ocp*OpD": [
      0.00014269521521360537,
      0.0,
      0.0,
      0.0
    ],
    "OpD*Otap": [
      6.668497435770582e-05,
      0.0,
      0.0,
      0.0
    ],
    "Obp*OpD": [
      0.0004271503252514292,
      0.0,
      0.0,
      0.0
    ],
    "O3pl3*OpD": [
      -6.685696889442573e-08,
      0.0,
      0.0,
      0.0
    ],
    "O3pq*OpD": [
      -3.701354840511029e-07,
      0.0,
      0.0,
      0.0
    ],
    "OpD*Opl2": [
      -9.14403333943925e-10,
      0.0,
      0.0,
      0.0
    ],
    "OpD*Opl3": [
      -9.14403333943925e-10,
      0.0,
      0.0,
      0.0
    ],
    "OpD*Opmu": [
      -4.4070290285141775e-09,
      0.0,
      0.0,
      0.0
    ],
    "OpD*Opta": [
      -4.4070290285141775e-09,
      0.0,
      0.0,
      0.0
    ],
    "OpD*OpqMi": [
      1.27319555297694e-09,
      0.0,
      0.0,
      0.0
    ],
    "OpD*Opui": [
      1.7084489297533358e-09,
      0.0,
      0.0,
      0.0
    ],
    "OpD*Opdi": [
      -2.7753755841311647e-09,
      0.0,
      0.0,
      0.0
    ],
    "O3pl1^2": [
      0.0003270395730560449,
      0.0,
      0.0,
      0.0
    ],
    "O3pl1*Opl1": [
      0.0006464682447338443,
      0.0,
      0.0,
      0.0
    ],
    "O3pl1*Ope": [
      -3.865612395552636e-07,
      0.0,
      0.0,
      0.0
    ],
    "O3pl1*Opd": [
      -4.5398314250364054e-05,
      0.0,
      0.0,
      0.0
    ],
    "O3pl1*OpWB": [
      0.007082901190771286,
      0.0,
      0.0,
      0.0
    ],
    "O3pl1*O3pl2": [
      7.655289241165136e-06,
      0.0,
      0.0,
      0.0
    ],
    "O3pl1*Oll": [
      -8.239417999212272e-06,
      0.0,
      0.0,
      0.0
    ],
    "O3pl1*Opt": [
      3.88790742993401e-06,
      0.0,
      0.0,
      0.0
    ],
    "O3pl1*OpQM": [
      3.688063013585508e-05,
      0.0,
      0.0,
      0.0
    ],
    "O3pl1*O3pQ3": [
      3.272970226515409e-05,
      0.0,
      0.0,
      0.0
    ],
    "O3pl1*OtW": [
      -9.483086954514216e-05,
      0.0,
      0.0,
      0.0
    ],
    "O3pl1*OtZ": [
      -0.00022788125178802886,
      0.0,
      0.0,
      0.0
    ],
    "O3pl1*Otp": [
      9.478041414706887e-06,
      0.0,
      0.0,
      0.0
    ],
    "O3pl1*OpG": [
      -0.0013204322041301259,
      0.0,
      0.0,
      0.0
    ],
    "O3pl1*OtG": [
      -3.044485424354501e-05,
      0.0,
      0.0,
      0.0
    ],
    "O3pl1*Ocp": [
      0.0011309812909684545,
      0.0,
      0.0,
      0.0
    ],
    "O3pl1*Otap": [
      0.0005281259336901094,
      0.0,
      0.0,
      0.0
    ],
    "O3pl1*Obp": [
      0.0033859168805282763,
      0.0,
      0.0,
      0.0
    ],
    "O3pl1*O3pl3": [
      -3.81209326658692e-07,
      0.0,
      0.0,
      0.0
    ],
    "O3pl1*O3pq": [
      -2.558959463370472e-06,
      0.0,
      0.0,
      0.0
    ],
    "O3pl1*Opl2": [
      2.6632902158607372e-08,
      0.0,
      0.0,
      0.0
    ],
    "O3pl1*Opl3": [
      2.6632902158607372e-08,
      0.0,
      0.0,
      0.0
    ],
    "O3pl1*Opmu": [
      2.5651683303767735e-08,
      0.0,
      0.0,
      0.0
    ],
    "O3pl1*Opta": [
      2.5651683303767735e-08,
      0.0,
      0.0,
      0.0
    ],
    "O3pl1*OpqMi": [
      -1.552057284958844e-08,
      0.0,
      0.0,
      0.0
    ],
    "O3pl1*Opui": [
      -2.8688925269987827e-08,
      0.0,
      0.0,
      0.0
    ],
    "O3pl1*Opdi": [
      3.602763524090087e-08,
      0.0,
      0.0,
      0.0
    ],
    "Opl1^2": [
      0.00031894656485532063,
      0.0,
      0.0,
      0.0
    ],
    "Ope*Opl1": [
      1.053963887320567e-08,
      0.0,
      0.0,
      0.0
    ],
    "Opd*Opl1": [
      -4.670869390023777e-05,
      0.0,
      0.0,
      0.0
    ],
    "Opl1*OpWB": [
      0.007310141806382028,
      0.0,
      0.0,
      0.0
    ],
    "O3pl2*Opl1": [
      8.585081415687536e-06,
      0.0,
      0.0,
      0.0
    ],
    "Oll*Opl1": [
      -9.088214095797751e-06,
      0.0,
      0.0,
      0.0
    ],
    "Opl1*Opt": [
      4.011118700333975e-06,
      0.0,
      0.0,
      0.0
    ],
    "Opl1*OpQM": [
      3.807878160531238e-05,
      0.0,
      0.0,
      0.0
    ],
    "O3pQ3*Opl1": [
      3.379512802441065e-05,
      0.0,
      0.0,
      0.0
    ],
    "Opl1*OtW": [
      -9.81342397476404e-05,
      0.0,
      0.0,
      0.0
    ],
    "Opl1*OtZ": [
      -0.0002350587405336698,
      0.0,
      0.0,
      0.0
    ],
    "Opl1*Otp": [
      9.675689338731806e-06,
      0.0,
      0.0,
      0.0
    ],
    "OpG*Opl1": [
      -0.0013273467548312373,
      0.0,
      0.0,
      0.0
    ],
    "Opl1*OtG": [
      -3.060587801799749e-05,
      0.0,
      0.0,
      0.0
    ],
    "Ocp*Opl1": [
      0.0011369868149333825,
      0.0,
      0.0,
      0.0
    ],
    "Opl1*Otap": [
      0.0005309042164361367,
      0.0,
      0.0,
      0.0
    ],
    "Obp*Opl1": [
      0.0034037184905649017,
      0.0,
      0.0,
      0.0
    ],
    "O3pl3*Opl1": [
      -3.5079981495849306e-07,
      0.0,
      0.0,
      0.0
    ],
    "O3pq*Opl1": [
      -2.168111506839397e-06,
      0.0,
      0.0,
      0.0
    ],
    "Opl1*Opl2": [
      9.966392484441223e-09,
      0.0,
      0.0,
      0.0
    ],
    "Opl1*Opl3": [
      9.966392484441223e-09,
      0.0,
      0.0,
      0.0
    ],
    "Opl1*Opmu": [
      1.1001197451437534e-08,
      0.0,
      0.0,
      0.0
    ],
    "Opl1*Opta": [
      1.1001197451437534e-08,
      0.0,
      0.0,
      0.0
    ],
    "Opl1*OpqMi": [
      -1.9935645985552914e-08,
      0.0,
      0.0,
      0.0
    ],
    "Opl1*Opui": [
      -3.526326911006663e-08,
      0.0,
      0.0,
      0.0
    ],
    "Opdi*Opl1": [
      2.74111522600682e-08,
      0.0,
      0.0,
      0.0
    ],
    "Ope^2": [
      1.9081702816544094e-05,
      0.0,
      0.0,
      0.0
    ],
    "Opd*Ope": [
      2.2439493200309345e-06,
      0.0,
      0.0,
      0.0
    ],
    "Ope*OpWB": [
      -0.0003545055940842047,
      0.0,
      0.0,
      0.0
    ],
    "O3pl2*Ope": [
      -3.949186690378213e-07,
      0.0,
      0.0,
      0.0
    ],
    "Oll*Ope": [
      4.5467758663100744e-07,
      0.0,
      0.0,
      0.0
    ],
    "Ope*Opt": [
      -1.9294779560604036e-07,
      0.0,
      0.0,
      0.0
    ],
    "Ope*OpQM": [
      -1.834769485378839e-06,
      0.0,
      0.0,
      0.0
    ],
    "O3pQ3*Ope": [
      -1.6233002391276569e-06,
      0.0,
      0.0,
      0.0
    ],
    "Ope*OtW": [
      4.7206204759242265e-06,
      0.0,
      0.0,
      0.0
    ],
    "Ope*OtZ": [
      1.1307079622787513e-05,
      0.0,
      0.0,
      0.0
    ],
    "Ope*Otp": [
      -4.654035560141888e-07,
      0.0,
      0.0,
      0.0
    ],
    "Ope*OpG": [
      6.384027471762289e-05,
      0.0,
      0.0,
      0.0
    ],
    "Ope*OtG": [
      1.47202504057912e-06,
      0.0,
      0.0,
      0.0
    ],
    "Ocp*Ope": [
      -5.4684693620161775e-05,
      0.0,
      0.0,
      0.0
    ],
    "Ope*Otap": [
      -2.553445126728513e-05,
      0.0,
      0.0,
      0.0
    ],
    "Obp*Ope": [
      -0.00016370577071003848,
      0.0,
      0.0,
      0.0
    ],
    "O3pl3*Ope": [
      1.8906565471602937e-08,
      0.0,
      0.0,
      0.0
    ],
    "O3pq*Ope": [
      1.1278712277229682e-07,
      0.0,
      0.0,
      0.0
    ],
    "Ope*Opl2": [
      2.1822093906478913e-09,
      0.0,
      0.0,
      0.0
    ],
    "Ope*Opl3": [
      2.1822093906478913e-09,
      0.0,
      0.0,
      0.0
    ],
    "Ope*Opmu": [
      4.3175417297197603e-10,
      0.0,
      0.0,
      0.0
    ],
    "Ope*Opta": [
      4.3175417297197603e-10,
      0.0,
      0.0,
      0.0
    ],
    "Ope*OpqMi": [
      8.259175584973607e-10,
      0.0,
      0.0,
      0.0
    ],
    "Ope*Opui": [
      -1.7920254534567022e-10,
      0.0,
      0.0,
      0.0
    ],
    "Opdi*Ope": [
      -1.3322671417513222e-09,
      0.0,
      0.0,
      0.0
    ],
    "Opd^2": [
      -1.7738215493355335e-08,
      0.0,
      0.0,
      0.0
    ],
    "Opd*OpWB": [
      -9.120650964957652e-07,
      0.0,
      0.0,
      0.0
    ],
    "O3pl2*Opd": [
      1.3035555530120655e-06,
      0.0,
      0.0,
      0.0
    ],
    "Oll*Opd": [
      -1.1605106686375724e-06,
      0.0,
      0.0,
      0.0
    ],
    "Opd*Opt": [
      -3.0621908802743497e-09,
      0.0,
      0.0,
      0.0
    ],
    "Opd*OpQM": [
      4.381269462972054e-08,
      0.0,
      0.0,
      0.0
    ],
    "O3pQ3*Opd": [
      5.996871285095204e-08,
      0.0,
      0.0,
      0.0
    ],
    "Opd*OtW": [
      -4.122817829410133e-07,
      0.0,
      0.0,
      0.0
    ],
    "Opd*OtZ": [
      2.518076061950767e-07,
      0.0,
      0.0,
      0.0
    ],
    "Opd*Otp": [
      -1.5031781239508866e-07,
      0.0,
      0.0,
      0.0
    ],
    "Opd*OpG": [
      5.018336578631655e-05,
      0.0,
      0.0,
      0.0
    ],
    "Opd*OtG": [
      1.1579205435051946e-06,
      0.0,
      0.0,
      0.0
    ],
    "Ocp*Opd": [
      -4.295966549932338e-05,
      0.0,
      0.0,
      0.0
    ],
    "Opd*Otap": [
      -2.0053295273273947e-05,
      0.0,
      0.0,
      0.0
    ],
    "Obp*Opd": [
      -0.0001284915853361875,
      0.0,
      0.0,
      0.0
    ],
    "O3pl3*Opd": [
      8.711157233144958e-08,
      0.0,
      0.0,
      0.0
    ],
    "O3pq*Opd": [
      5.307539602731113e-07,
      0.0,
      0.0,
      0.0
    ],
    "Opd*Opl2": [
      -2.885284834141204e-10,
      0.0,
      0.0,
      0.0
    ],
    "Opd*Opl3": [
      -2.885284834141204e-10,
      0.0,
      0.0,
      0.0
    ],
    "Opd*Opmu": [
      -3.2161101050108178e-09,
      0.0,
      0.0,
      0.0
    ],
    "Opd*Opta": [
      -3.2161101050108178e-09,
      0.0,
      0.0,
      0.0
    ],
    "Opd*OpqMi": [
      7.019595633650308e-09,
      0.0,
      0.0,
      0.0
    ],
    "Opd*Opui": [
      1.3477875439847065e-08,
      0.0,
      0.0,
      0.0
    ],
    "Opd*Opdi": [
      -4.969040696913025e-09,
      0.0,
      0.0,
      0.0
    ],
    "OpWB^2": [
      0.011305444880158189,
      0.0,
      0.0,
      0.0
    ],
    "O3pl2*OpWB": [
      -0.00022737241357189658,
      0.0,
      0.0,
      0.0
    ],
    "Oll*OpWB": [
      0.00022393076209044655,
      0.0,
      0.0,
      0.0
    ],
    "Opt*OpWB": [
      1.2916898550403274e-05,
      0.0,
      0.0,
      0.0
    ],
    "OpQM*OpWB": [
      0.00011427849412618416,
      0.0,
      0.0,
      0.0
    ],
    "O3pQ3*OpWB": [
      0.00010031092694038611,
      0.0,
      0.0,
      0.0
    ],
    "OpWB*OtW": [
      -0.0002456663365316522,
      0.0,
      0.0,
      0.0
    ],
    "OpWB*OtZ": [
      -0.0007672150089202038,
      0.0,
      0.0,
      0.0
    ],
    "OpWB*Otp": [
      4.106365741552259e-05,
      0.0,
      0.0,
      0.0
    ],
    "OpG*OpWB": [
      -0.007942435491187021,
      0.0,
      0.0,
      0.0
    ],
    "OpWB*OtG": [
      -0.0001831361781872819,
      0.0,
      0.0,
      0.0
    ],
    "Ocp*OpWB": [
      0.006803380050517953,
      0.0,
      0.0,
      0.0
    ],
    "OpWB*Otap": [
      0.0031767678458514983,
      0.0,
      0.0,
      0.0
    ],
    "Obp*OpWB": [
      0.02036680652065884,
      0.0,
      0.0,
      0.0
    ],
    "O3pl3*OpWB": [
      -2.3988586635192224e-06,
      0.0,
      0.0,
      0.0
    ],
    "O3pq*OpWB": [
      -1.3457378772543204e-05,
      0.0,
      0.0,
      0.0
    ],
    "Opl2*OpWB": [
      -1.3179796114558153e-07,
      0.0,
      0.0,
      0.0
    ],
    "Opl3*OpWB": [
      -1.3179796114558153e-07,
      0.0,
      0.0,
      0.0
    ],
    "Opmu*OpWB": [
      9.74464073712106e-08,
      0.0,
      0.0,
      0.0
    ],
    "Opta*OpWB": [
      9.74464073712106e-08,
      0.0,
      0.0,
      0.0
    ],
    "OpqMi*OpWB": [
      -1.1907532031115526e-07,
      0.0,
      0.0,
      0.0
    ],
    "Opui*OpWB": [
      -4.5211267336729747e-07,
      0.0,
      0.0,
      0.0
    ],
    "Opdi*OpWB": [
      1.2867732375707004e-07,
      0.0,
      0.0,
      0.0
    ],
    "O3pl2^2": [
      -4.636200820746679e-07,
      0.0,
      0.0,
      0.0
    ],
    "O3pl2*Oll": [
      8.700034196518621e-07,
      0.0,
      0.0,
      0.0
    ],
    "O3pl2*Opt": [
      -1.231795159308613e-07,
      0.0,
      0.0,
      0.0
    ],
    "O3pl2*OpQM": [
      -1.1967515438076002e-06,
      0.0,
      0.0,
      0.0
    ],
    "O3pl2*O3pQ3": [
      -1.0616724210320032e-06,
      0.0,
      0.0,
      0.0
    ],
    "O3pl2*OtW": [
      3.30264316946237e-06,
      0.0,
      0.0,
      0.0
    ],
    "O3pl2*OtZ": [
      7.175620472140404e-06,
      0.0,
      0.0,
      0.0
    ],
    "O3pl2*Otp": [
      -1.9752950901335997e-07,
      0.0,
      0.0,
      0.0
    ],
    "O3pl2*OpG": [
      6.89381519584454e-06,
      0.0,
      0.0,
      0.0
    ],
    "O3pl2*OtG": [
      1.6098136103430935e-07,
      0.0,
      0.0,
      0.0
    ],
    "O3pl2*Ocp": [
      -5.987762218795339e-06,
      0.0,
      0.0,
      0.0
    ],
    "O3pl2*Otap": [
      -2.769989082645244e-06,
      0.0,
      0.0,
      0.0
    ],
    "O3pl2*Obp": [
      -1.7868256683971535e-05,
      0.0,
      0.0,
      0.0
    ],
    "O3pl2*O3pl3": [
      -3.306846361320686e-08,
      0.0,
      0.0,
      0.0
    ],
    "O3pl2*O3pq": [
      -3.8134331493398586e-07,
      0.0,
      0.0,
      0.0
    ],
    "O3pl2*Opl2": [
      1.703918694487691e-08,
      0.0,
      0.0,
      0.0
    ],
    "O3pl2*Opl3": [
      1.703918694487691e-08,
      0.0,
      0.0,
      0.0
    ],
    "O3pl2*Opmu": [
      1.7294253821209944e-08,
      0.0,
      0.0,
      0.0
    ],
    "O3pl2*Opta": [
      1.7294253821209944e-08,
      0.0,
      0.0,
      0.0
    ],
    "O3pl2*OpqMi": [
      8.687867409357523e-09,
      0.0,
      0.0,
      0.0
    ],
    "O3pl2*Opui": [
      9.641105140009989e-09,
      0.0,
      0.0,
      0.0
    ],
    "O3pl2*Opdi": [
      1.0594978985954008e-08,
      0.0,
      0.0,
      0.0
    ],
    "Oll^2": [
      -4.0037763435374974e-07,
      0.0,
      0.0,
      0.0
    ],
    "Oll*Opt": [
      1.2141030575403246e-07,
      0.0,
      0.0,
      0.0
    ],
    "Oll*OpQM": [
      1.2146989270601622e-06,
      0.0,
      0.0,
      0.0
    ],
    "O3pQ3*Oll": [
      1.112085014888109e-06,
      0.0,
      0.0,
      0.0
    ],
    "Oll*OtW": [
      -3.262136296504796e-06,
      0.0,
      0.0,
      0.0
    ],
    "Oll*OtZ": [
      -7.071529029812922e-06,
      0.0,
      0.0,
      0.0
    ],
    "Oll*Otp": [
      1.9152797239263606e-07,
      0.0,
      0.0,
      0.0
    ],
    "Oll*OpG": [
      -5.858348788965328e-06,
      0.0,
      0.0,
      0.0
    ],
    "Oll*OtG": [
      -1.2617340796792908e-07,
      0.0,
      0.0,
      0.0
    ],
    "Ocp*Oll": [
      4.867449610881115e-06,
      0.0,
      0.0,
      0.0
    ],
    "Oll*Otap": [
      2.287209067124856e-06,
      0.0,
      0.0,
      0.0
    ],
    "Obp*Oll": [
      1.540681639786996e-05,
      0.0,
      0.0,
      0.0
    ],
    "O3pl3*Oll": [
      1.1235786299024428e-07,
      0.0,
      0.0,
      0.0
    ],
    "O3pq*Oll": [
      4.4118748128567427e-07,
      0.0,
      0.0,
      0.0
    ],
    "Oll*Opl2": [
      1.4344976269193932e-08,
      0.0,
      0.0,
      0.0
    ],
    "Oll*Opl3": [
      1.4344976269193932e-08,
      0.0,
      0.0,
      0.0
    ],
    "Oll*Opmu": [
      1.6748783245040392e-08,
      0.0,
      0.0,
      0.0
    ],
    "Oll*Opta": [
      1.6748783245040392e-08,
      0.0,
      0.0,
      0.0
    ],
    "Oll*OpqMi": [
      1.687202596249924e-08,
      0.0,
      0.0,
      0.0
    ],
    "Oll*Opui": [
      1.1424805060640611e-08,
      0.0,
      0.0,
      0.0
    ],
    "Oll*Opdi": [
      1.304273159254941e-08,
      0.0,
      0.0,
      0.0
    ],
    "Opt^2": [
      3.0419582038301146e-09,
      0.0,
      0.0,
      0.0
    ],
    "OpQM*Opt": [
      6.410834358820334e-08,
      0.0,
      0.0,
      0.0
    ],
    "O3pQ3*Opt": [
      5.746633580468228e-08,
      0.0,
      0.0,
      0.0
    ],
    "Opt*OtW": [
      -2.0607850873416365e-07,
      0.0,
      0.0,
      0.0
    ],
    "Opt*OtZ": [
      -3.4801992744396037e-07,
      0.0,
      0.0,
      0.0
    ],
    "Opt*Otp": [
      2.3421346762730438e-08,
      0.0,
      0.0,
      0.0
    ],
    "OpG*Opt": [
      -4.393348368137996e-06,
      0.0,
      0.0,
      0.0
    ],
    "Opt*OtG": [
      -1.0130155044745313e-07,
      0.0,
      0.0,
      0.0
    ],
    "Ocp*Opt": [
      3.7632812600028505e-06,
      0.0,
      0.0,
      0.0
    ],
    "Opt*Otap": [
      1.7572252046631449e-06,
      0.0,
      0.0,
      0.0
    ],
    "Obp*Opt": [
      1.1265873835677325e-05,
      0.0,
      0.0,
      0.0
    ],
    "O3pl3*Opt": [
      -1.1676787167069807e-09,
      0.0,
      0.0,
      0.0
    ],
    "O3pq*Opt": [
      -7.208104688176524e-09,
      0.0,
      0.0,
      0.0
    ],
    "Opl2*Opt": [
      3.175446910927489e-11,
      0.0,
      0.0,
      0.0
    ],
    "Opl3*Opt": [
      3.175446910927489e-11,
      0.0,
      0.0,
      0.0
    ],
    "Opmu*Opt": [
      2.7662457184158055e-11,
      0.0,
      0.0,
      0.0
    ],
    "Opt*Opta": [
      2.7662457184158048e-11,
      0.0,
      0.0,
      0.0
    ],
    "OpqMi*Opt": [
      -8.01280996215348e-11,
      0.0,
      0.0,
      0.0
    ],
    "Opt*Opui": [
      -1.2686949106743005e-10,
      0.0,
      0.0,
      0.0
    ],
    "Opdi*Opt": [
      8.418016163943289e-11,
      0.0,
      0.0,
      0.0
    ],
    "OpQM^2": [
      2.8871571054165593e-07,
      0.0,
      0.0,
      0.0
    ],
    "O3pQ3*OpQM": [
      5.08085188395033e-07,
      0.0,
      0.0,
      0.0
    ],
    "OpQM*OtW": [
      -1.2986525912680838e-06,
      0.0,
      0.0,
      0.0
    ],
    "OpQM*OtZ": [
      -3.7965754632537933e-06,
      0.0,
      0.0,
      0.0
    ],
    "OpQM*Otp": [
      2.1016036544157437e-07,
      0.0,
      0.0,
      0.0
    ],
    "OpG*OpQM": [
      -4.087170278144176e-05,
      0.0,
      0.0,
      0.0
    ],
    "OpQM*OtG": [
      -9.424171529885569e-07,
      0.0,
      0.0,
      0.0
    ],
    "Ocp*OpQM": [
      3.5010133559473484e-05,
      0.0,
      0.0,
      0.0
    ],
    "OpQM*Otap": [
      1.6347619234094463e-05,
      0.0,
      0.0,
      0.0
    ],
    "Obp*OpQM": [
      0.00010480740619714992,
      0.0,
      0.0,
      0.0
    ],
    "O3pl3*OpQM": [
      -1.0266101628108185e-08,
      0.0,
      0.0,
      0.0
    ],
    "O3pq*OpQM": [
      -6.155685610180249e-08,
      0.0,
      0.0,
      0.0
    ],
    "Opl2*OpQM": [
      1.3999256496834673e-09,
      0.0,
      0.0,
      0.0
    ],
    "Opl3*OpQM": [
      1.3999256496834673e-09,
      0.0,
      0.0,
      0.0
    ],
    "Opmu*OpQM": [
      -2.8470487294973827e-09,
      0.0,
      0.0,
      0.0
    ],
    "OpQM*Opta": [
      -2.8470487294973827e-09,
      0.0,
      0.0,
      0.0
    ],
    "OpQM*OpqMi": [
      -1.3869047308580853e-09,
      0.0,
      0.0,
      0.0
    ],
    "OpQM*Opui": [
      2.5286571216459974e-09,
      0.0,
      0.0,
      0.0
    ],
    "Opdi*OpQM": [
      1.5587984210110126e-09,
      0.0,
      0.0,
      0.0
    ],
    "O3pQ3^2": [
      2.2187309386325502e-07,
      0.0,
      0.0,
      0.0
    ],
    "O3pQ3*OtW": [
      -1.0830687842481884e-06,
      0.0,
      0.0,
      0.0
    ],
    "O3pQ3*OtZ": [
      -3.415508124534531e-06,
      0.0,
      0.0,
      0.0
    ],
    "O3pQ3*Otp": [
      1.8499086287519406e-07,
      0.0,
      0.0,
      0.0
    ],
    "O3pQ3*OpG": [
      -3.613330900993419e-05,
      0.0,
      0.0,
      0.0
    ],
    "O3pQ3*OtG": [
      -8.331595673244116e-07,
      0.0,
      0.0,
      0.0
    ],
    "O3pQ3*Ocp": [
      3.095129119401222e-05,
      0.0,
      0.0,
      0.0
    ],
    "O3pQ3*Otap": [
      1.4452384832630218e-05,
      0.0,
      0.0,
      0.0
    ],
    "O3pQ3*Obp": [
      9.26567315999092e-05,
      0.0,
      0.0,
      0.0
    ],
    "O3pl3*O3pQ3": [
      -5.217175200436375e-09,
      0.0,
      0.0,
      0.0
    ],
    "O3pq*O3pQ3": [
      -4.5286401396342364e-08,
      0.0,
      0.0,
      0.0
    ],
    "O3pQ3*Opl2": [
      3.753338224529574e-09,
      0.0,
      0.0,
      0.0
    ],
    "O3pQ3*Opl3": [
      3.753338224529574e-09,
      0.0,
      0.0,
      0.0
    ],
    "O3pQ3*Opmu": [
      2.420194425991157e-09,
      0.0,
      0.0,
      0.0
    ],
    "O3pQ3*Opta": [
      2.420194425991157e-09,
      0.0,
      0.0,
      0.0
    ],
    "O3pQ3*OpqMi": [
      9.1932228023538e-10,
      0.0,
      0.0,
      0.0
    ],
    "O3pQ3*Opui": [
      8.311132523807064e-09,
      0.0,
      0.0,
      0.0
    ],
    "O3pQ3*Opdi": [
      -1.8401888807667954e-09,
      0.0,
      0.0,
      0.0
    ],
    "OtW^2": [
      -3.899819858409704e-07,
      0.0,
      0.0,
      0.0
    ],
    "OtW*OtZ": [
      1.2941674333237362e-05,
      0.0,
      0.0,
      0.0
    ],
    "Otp*OtW": [
      -4.677007238062553e-07,
      0.0,
      0.0,
      0.0
    ],
    "OpG*OtW": [
      0.00010058771226691462,
      0.0,
      0.0,
      0.0
    ],
    "OtG*OtW": [
      2.319345145151642e-06,
      0.0,
      0.0,
      0.0
    ],
    "Ocp*OtW": [
      -8.616203880073197e-05,
      0.0,
      0.0,
      0.0
    ],
    "Otap*OtW": [
      -4.023247156012342e-05,
      0.0,
      0.0,
      0.0
    ],
    "Obp*OtW": [
      -0.0002579373136072869,
      0.0,
      0.0,
      0.0
    ],
    "O3pl3*OtW": [
      2.6734536152001457e-08,
      0.0,
      0.0,
      0.0
    ],
    "O3pq*OtW": [
      1.6503284046909992e-07,
      0.0,
      0.0,
      0.0
    ],
    "Opl2*OtW": [
      -7.27033035922464e-10,
      0.0,
      0.0,
      0.0
    ],
    "Opl3*OtW": [
      -7.27033035922464e-10,
      0.0,
      0.0,
      0.0
    ],
    "Opmu*OtW": [
      -6.333445587915501e-10,
      0.0,
      0.0,
      0.0
    ],
    "Opta*OtW": [
      -6.333445587915501e-10,
      0.0,
      0.0,
      0.0
    ],
    "OpqMi*OtW": [
      1.8345693429819189e-09,
      0.0,
      0.0,
      0.0
    ],
    "Opui*OtW": [
      2.9047347930547038e-09,
      0.0,
      0.0,
      0.0
    ],
    "Opdi*OtW": [
      -1.9273431487879842e-09,
      0.0,
      0.0,
      0.0
    ],
    "OtZ^2": [
      9.869055505114226e-06,
      0.0,
      0.0,
      0.0
    ],
    "Otp*OtZ": [
      -1.3880945895368574e-06,
      0.0,
      0.0,
      0.0
    ],
    "OpG*OtZ": [
      0.0002584825558183852,
      0.0,
      0.0,
      0.0
    ],
    "OtG*OtZ": [
      5.960074520364168e-06,
      0.0,
      0.0,
      0.0
    ],
    "Ocp*OtZ": [
      -0.00022141257119595115,
      0.0,
      0.0,
      0.0
    ],
    "Otap*OtZ": [
      -0.0001033863067504297,
      0.0,
      0.0,
      0.0
    ],
    "Obp*OtZ": [
      -0.0006628274424337391,
      0.0,
      0.0,
      0.0
    ],
    "O3pl3*OtZ": [
      6.870035193614133e-08,
      0.0,
      0.0,
      0.0
    ],
    "O3pq*OtZ": [
      4.2408868277295453e-07,
      0.0,
      0.0,
      0.0
    ],
    "Opl2*OtZ": [
      -1.8682735003552804e-09,
      0.0,
      0.0,
      0.0
    ],
    "Opl3*OtZ": [
      -1.8682735003552804e-09,
      0.0,
      0.0,
      0.0
    ],
    "Opmu*OtZ": [
      -1.6275200676171901e-09,
      0.0,
      0.0,
      0.0
    ],
    "Opta*OtZ": [
      -1.6275200676171901e-09,
      0.0,
      0.0,
      0.0
    ],
    "OpqMi*OtZ": [
      4.714335000896503e-09,
      0.0,
      0.0,
      0.0
    ],
    "Opui*OtZ": [
      7.464363751419461e-09,
      0.0,
      0.0,
      0.0
    ],
    "Opdi*OtZ": [
      -4.952737981711069e-09,
      0.0,
      0.0,
      0.0
    ],
    "Otp^2": [
      -4.235196522680259e-08,
      0.0,
      0.0,
      0.0
    ],
    "OpG*Otp": [
      3.6667727481606856e-05,
      0.0,
      0.0,
      0.0
    ],
    "OtG*Otp": [
      8.464607638091119e-07,
      0.0,
      0.0,
      0.0
    ],
    "Ocp*Otp": [
      1.2742679542122132e-05,
      0.0,
      0.0,
      0.0
    ],
    "Otap*Otp": [
      5.950062224779203e-06,
      0.0,
      0.0,
      0.0
    ],
    "Obp*Otp": [
      3.814687506240383e-05,
      0.0,
      0.0,
      0.0
    ],
    "O3pl3*Otp": [
      -3.953825044461917e-09,
      0.0,
      0.0,
      0.0
    ],
    "O3pq*Otp": [
      -2.4407043163027374e-08,
      0.0,
      0.0,
      0.0
    ],
    "Opl2*Otp": [
      1.0752239759230745e-10,
      0.0,
      0.0,
      0.0
    ],
    "Opl3*Otp": [
      1.0752239759230745e-10,
      0.0,
      0.0,
      0.0
    ],
    "Opmu*Otp": [
      9.366661774441308e-11,
      0.0,
      0.0,
      0.0
    ],
    "Opta*Otp": [
      9.366661774441308e-11,
      0.0,
      0.0,
      0.0
    ],
    "OpqMi*Otp": [
      -2.713181995319908e-10,
      0.0,
      0.0,
      0.0
    ],
    "Opui*Otp": [
      -4.2958714925898564e-10,
      0.0,
      0.0,
      0.0
    ],
    "Opdi*Otp": [
      2.8503870677328095e-10,
      0.0,
      0.0,
      0.0
    ],
    "OpG^2": [
      -0.0067764354437159615,
      0.0,
      0.0,
      0.0
    ],
    "OpG*OtG": [
      -0.0003121510907076768,
      0.0,
      0.0,
      0.0
    ],
    "Ocp*OpG": [
      -0.0024574033381317036,
      0.0,
      0.0,
      0.0
    ],
    "OpG*Otap": [
      -0.0011474590351998053,
      0.0,
      0.0,
      0.0
    ],
    "Obp*OpG": [
      -0.007356557763833761,
      0.0,
      0.0,
      0.0
    ],
    "O3pl3*OpG": [
      7.624882059171163e-07,
      0.0,
      0.0,
      0.0
    ],
    "O3pq*OpG": [
      4.706855347376918e-06,
      0.0,
      0.0,
      0.0
    ],
    "OpG*Opl2": [
      -2.0735505267462537e-08,
      0.0,
      0.0,
      0.0
    ],
    "OpG*Opl3": [
      -2.0735505267462537e-08,
      0.0,
      0.0,
      0.0
    ],
    "OpG*Opmu": [
      -1.806344249306092e-08,
      0.0,
      0.0,
      0.0
    ],
    "OpG*Opta": [
      -1.806344249306092e-08,
      0.0,
      0.0,
      0.0
    ],
    "OpG*OpqMi": [
      5.232323759079332e-08,
      0.0,
      0.0,
      0.0
    ],
    "OpG*Opui": [
      8.284512618542274e-08,
      0.0,
      0.0,
      0.0
    ],
    "Opdi*OpG": [
      -5.496921328092603e-08,
      0.0,
      0.0,
      0.0
    ],
    "OtG^2": [
      -3.5987683673175415e-06,
      0.0,
      0.0,
      0.0
    ],
    "Ocp*OtG": [
      -5.666265166515683e-05,
      0.0,
      0.0,
      0.0
    ],
    "Otap*OtG": [
      -2.645803828890171e-05,
      0.0,
      0.0,
      0.0
    ],
    "Obp*OtG": [
      -0.0001696270463861383,
      0.0,
      0.0,
      0.0
    ],
    "O3pl3*OtG": [
      1.758140511175476e-08,
      0.0,
      0.0,
      0.0
    ],
    "O3pq*OtG": [
      1.0853037466347146e-07,
      0.0,
      0.0,
      0.0
    ],
    "Opl2*OtG": [
      -4.781179767439076e-10,
      0.0,
      0.0,
      0.0
    ],
    "Opl3*OtG": [
      -4.781179767439076e-10,
      0.0,
      0.0,
      0.0
    ],
    "Opmu*OtG": [
      -4.165057212936233e-10,
      0.0,
      0.0,
      0.0
    ],
    "Opta*OtG": [
      -4.165057212936233e-10,
      0.0,
      0.0,
      0.0
    ],
    "OpqMi*OtG": [
      1.2064659226248133e-09,
      0.0,
      0.0,
      0.0
    ],
    "Opui*OtG": [
      1.910237710822621e-09,
      0.0,
      0.0,
      0.0
    ],
    "Opdi*OtG": [
      -1.2674766637262105e-09,
      0.0,
      0.0,
      0.0
    ],
    "Ocp^2": [
      -0.0019320874230247841,
      0.0,
      0.0,
      0.0
    ],
    "Ocp*Otap": [
      0.0009828974900113684,
      0.0,
      0.0,
      0.0
    ],
    "Obp*Ocp": [
      0.00630152531757857,
      0.0,
      0.0,
      0.0
    ],
    "O3pl3*Ocp": [
      -6.531368186304839e-07,
      0.0,
      0.0,
      0.0
    ],
    "O3pq*Ocp": [
      -4.0318269889066515e-06,
      0.0,
      0.0,
      0.0
    ],
    "Ocp*Opl2": [
      1.7761746133235644e-08,
      0.0,
      0.0,
      0.0
    ],
    "Ocp*Opl3": [
      1.7761746133235644e-08,
      0.0,
      0.0,
      0.0
    ],
    "Ocp*Opmu": [
      1.5472894232169873e-08,
      0.0,
      0.0,
      0.0
    ],
    "Ocp*Opta": [
      1.5472894232169873e-08,
      0.0,
      0.0,
      0.0
    ],
    "Ocp*OpqMi": [
      -4.481935940162265e-08,
      0.0,
      0.0,
      0.0
    ],
    "Ocp*Opui": [
      -7.096398571923586e-08,
      0.0,
      0.0,
      0.0
    ],
    "Ocp*Opdi": [
      4.708586546822892e-08,
      0.0,
      0.0,
      0.0
    ],
    "Otap^2": [
      -0.0007649098276477278,
      0.0,
      0.0,
      0.0
    ],
    "Obp*Otap": [
      0.0029424319764671542,
      0.0,
      0.0,
      0.0
    ],
    "O3pl3*Otap": [
      -3.049754723329178e-07,
      0.0,
      0.0,
      0.0
    ],
    "O3pq*Otap": [
      -1.882619851204668e-06,
      0.0,
      0.0,
      0.0
    ],
    "Opl2*Otap": [
      8.293663382504177e-09,
      0.0,
      0.0,
      0.0
    ],
    "Opl3*Otap": [
      8.293663382504177e-09,
      0.0,
      0.0,
      0.0
    ],
    "Opmu*Otap": [
      7.224907695003189e-09,
      0.0,
      0.0,
      0.0
    ],
    "Opta*Otap": [
      7.224907695003189e-09,
      0.0,
      0.0,
      0.0
    ],
    "OpqMi*Otap": [
      -2.0927935638094655e-08,
      0.0,
      0.0,
      0.0
    ],
    "Opui*Otap": [
      -3.313589809364986e-08,
      0.0,
      0.0,
      0.0
    ],
    "Opdi*Otap": [
      2.198625716965072e-08,
      0.0,
      0.0,
      0.0
    ],
    "Obp^2": [
      0.005849638691724072,
      0.0,
      0.0,
      0.0
    ],
    "O3pl3*Obp": [
      -1.955250348766416e-06,
      0.0,
      0.0,
      0.0
    ],
    "O3pq*Obp": [
      -1.2069800540039024e-05,
      0.0,
      0.0,
      0.0
    ],
    "Obp*Opl2": [
      5.31721062587309e-08,
      0.0,
      0.0,
      0.0
    ],
    "Obp*Opl3": [
      5.31721062587309e-08,
      0.0,
      0.0,
      0.0
    ],
    "Obp*Opmu": [
      4.632012923006267e-08,
      0.0,
      0.0,
      0.0
    ],
    "Obp*Opta": [
      4.632012923006267e-08,
      0.0,
      0.0,
      0.0
    ],
    "Obp*OpqMi": [
      -1.34172604578106e-07,
      0.0,
      0.0,
      0.0
    ],
    "Obp*Opui": [
      -2.1243995724866782e-07,
      0.0,
      0.0,
      0.0
    ],
    "Obp*Opdi": [
      1.4095768643355152e-07,
      0.0,
      0.0,
      0.0
    ],
    "O3pl3^2": [
      1.9261932117567204e-10,
      0.0,
      0.0,
      0.0
    ],
    "O3pl3*O3pq": [
      2.4735479348442124e-08,
      0.0,
      0.0,
      0.0
    ],
    "O3pl3*Opl2": [
      1.9813016355488e-09,
      0.0,
      0.0,
      0.0
    ],
    "O3pl3*Opl3": [
      1.9813016355488e-09,
      0.0,
      0.0,
      0.0
    ],
    "O3pl3*Opmu": [
      1.934084323824651e-09,
      0.0,
      0.0,
      0.0
    ],
    "O3pl3*Opta": [
      1.934084323824651e-09,
      0.0,
      0.0,
      0.0
    ],
    "O3pl3*OpqMi": [
      1.4070719697814414e-09,
      0.0,
      0.0,
      0.0
    ],
    "O3pl3*Opui": [
      4.0467638125828615e-10,
      0.0,
      0.0,
      0.0
    ],
    "O3pl3*Opdi": [
      3.342493723604927e-09,
      0.0,
      0.0,
      0.0
    ],
    "O3pq^2": [
      4.7050449949361444e-08,
      0.0,
      0.0,
      0.0
    ],
    "O3pq*Opl2": [
      9.613567736727349e-09,
      0.0,
      0.0,
      0.0
    ],
    "O3pq*Opl3": [
      9.613567736727349e-09,
      0.0,
      0.0,
      0.0
    ],
    "O3pq*Opmu": [
      8.01564823835758e-09,
      0.0,
      0.0,
      0.0
    ],
    "O3pq*Opta": [
      8.01564823835758e-09,
      0.0,
      0.0,
      0.0
    ],
    "O3pq*OpqMi": [
      4.9907900656380496e-09,
      0.0,
      0.0,
      0.0
    ],
    "O3pq*Opui": [
      1.0284571259814528e-08,
      0.0,
      0.0,
      0.0
    ],
    "O3pq*Opdi": [
      6.814640778871824e-09,
      0.0,
      0.0,
      0.0
    ],
    "Opl2^2": [
      1.8633863535538853e-10,
      0.0,
      0.0,
      0.0
    ],
    "Opl2*Opl3": [
      3.7267727071077706e-10,
      0.0,
      0.0,
      0.0
    ],
    "Opl2*Opmu": [
      2.643767968879757e-09,
      0.0,
      0.0,
      0.0
    ],
    "Opl2*Opta": [
      2.643767968879757e-09,
      0.0,
      0.0,
      0.0
    ],
    "Opl2*OpqMi": [
      4.272794273393093e-09,
      0.0,
      0.0,
      0.0
    ],
    "Opl2*Opui": [
      3.0667612999312008e-09,
      0.0,
      0.0,
      0.0
    ],
    "Opdi*Opl2": [
      1.9784960051213937e-09,
      0.0,
      0.0,
      0.0
    ],
    "Opl3^2": [
      1.8633863535538853e-10,
      0.0,
      0.0,
      0.0
    ],
    "Opl3*Opmu": [
      2.643767968879757e-09,
      0.0,
      0.0,
      0.0
    ],
    "Opl3*Opta": [
      2.643767968879757e-09,
      0.0,
      0.0,
      0.0
    ],
    "Opl3*OpqMi": [
      4.272794273393093e-09,
      0.0,
      0.0,
      0.0
    ],
    "Opl3*Opui": [
      3.0667612999312008e-09,
      0.0,
      0.0,
      0.0
    ],
    "Opdi*Opl3": [
      1.9784960051213937e-09,
      0.0,
      0.0,
      0.0
    ],
    "Opmu^2": [
      4.169172040893163e-10,
      0.0,
      0.0,
      0.0
    ],
    "Opmu*Opta": [
      8.338344081786326e-10,
      0.0,
      0.0,
      0.0
    ],
    "Opmu*OpqMi": [
      -3.3876296601293974e-10,
      0.0,
      0.0,
      0.0
    ],
    "Opmu*Opui": [
      -2.023280042486983e-09,
      0.0,
      0.0,
      0.0
    ],
    "Opdi*Opmu": [
      -1.0868895538900792e-10,
      0.0,
      0.0,
      0.0
    ],
    "Opta^2": [
      4.169172040893163e-10,
      0.0,
      0.0,
      0.0
    ],
    "OpqMi*Opta": [
      -3.3876296601293974e-10,
      0.0,
      0.0,
      0.0
    ],
    "Opta*Opui": [
      -2.023280042486983e-09,
      0.0,
      0.0,
      0.0
    ],
    "Opdi*Opta": [
      -1.0868895538900792e-10,
      0.0,
      0.0,
      0.0
    ],
    "OpqMi^2": [
      -2.2129647152576557e-10,
      0.0,
      0.0,
      0.0
    ],
    "OpqMi*Opui": [
      3.124423394531276e-09,
      0.0,
      0.0,
      0.0
    ],
    "Opdi*OpqMi": [
      1.685174085399086e-09,
      0.0,
      0.0,
      0.0
    ],
    "Opui^2": [
      -1.215635738978828e-10,
      0.0,
      0.0,
      0.0
    ],
    "Opdi*Opui": [
      2.3817165546352936e-09,
      0.0,
      0.0,
      0.0
    ],
    "Opdi^2": [
      -3.081700521047539e-10,
      0.0,
      0.0,
      0.0
    ]
  }
}
